[{"2": {"A": 6}, "27": {"A": 6}, "43": {"A": 6}, "47": {"A": 6}, "74": {"A": 6}, "79": {"A": 6}, "94": {"A": 6}, "109": {"A": 6}, "132": {"A": 6}, "142": {"A": 6}, "153": {"A": 6}, "179": {"A": 6}, "180": {"A": 6}, "198": {"A": 6}, "219": {"A": 6}, "225": {"A": 6}, "250": {"A": 6}, "257": {"A": 6}, "278": {"A": 6}, "292": {"A": 6}, "313": {"A": 6}, "322": {"A": 6}, "337": {"A": 6}, "359": {"A": 6}, "364": {"A": 6}, "383": {"A": 6}, "392": {"A": 6}, "407": {"A": 6}, "427": {"A": 6}, "445": {"A": 6}, "458": {"A": 6}, "478": {"A": 6}, "483": {"A": 6}, "507": {"A": 6}, "513": {"A": 6}, "538": {"A": 6}, "540": {"A": 6}, "568": {"A": 6}, "579": {"A": 6}, "599": {"A": 6}, "611": {"A": 6}, "616": {"A": 6}, "636": {"A": 6}, "650": {"A": 6}, "673": {"A": 6}, "676": {"A": 6}, "692": {"A": 6}, "718": {"A": 6}, "729": {"A": 6}, "735": {"A": 6}, "764": {"A": 6}, "768": {"A": 6}, "785": {"A": 6}, "808": {"A": 6}, "820": {"A": 6}, "829": {"A": 6}, "846": {"A": 6}, "855": {"A": 6}, "880": {"A": 6}, "890": {"A": 6}, "913": {"A": 6}, "923": {"A": 6}, "944": {"A": 6}, "959": {"A": 6}, "973": {"A": 6}, "977": {"A": 6}, "1000": {"A": 6}, "1009": {"A": 6}, "1029": {"A": 6}, "1044": {"A": 6}, "1051": {"A": 6}, "1069": {"A": 6}, "1080": {"A": 6}, "1108": {"A": 6}, "1116": {"A": 6}, "1126": {"A": 6}, "1150": {"A": 6}, "1155": {"A": 6}, "1175": {"A": 6}, "1192": {"A": 6}, "1210": {"A": 6}, "1229": {"A": 6}, "1244": {"A": 6}, "1258": {"A": 6}, "1263": {"A": 6}, "1280": {"A": 6}, "1294": {"A": 6}, "1317": {"A": 6}, "1325": {"A": 6}, "1335": {"A": 6}, "1360": {"A": 6}, "1370": {"A": 6}, "1382": {"A": 6}, "1401": {"A": 6}, "1418": {"A": 6}, "1431": {"A": 6}, "1451": {"A": 6}, "1459": {"A": 6}, "1476": {"A": 6}, "1489": {"A": 6}}, {"1": {"A": 0}, "23": {"A": 0}, "32": {"A": 0}, "45": {"A": 0}, "64": {"A": 0}, "86": {"A": 0}, "104": {"A": 0}, "105": {"A": 0}, "123": {"A": 0}, "147": {"A": 0}, "154": {"A": 0}, "167": {"A": 0}, "187": {"A": 0}, "199": {"A": 0}, "214": {"A": 0}, "226": {"A": 0}, "254": {"A": 0}, "269": {"A": 0}, "283": {"A": 0}, "289": {"A": 0}, "314": {"A": 0}, "329": {"A": 0}, "331": {"A": 0}, "356": {"A": 0}, "367": {"A": 0}, "385": {"A": 0}, "401": {"A": 0}, "416": {"A": 0}, "430": {"A": 0}, "444": {"A": 0}, "457": {"A": 0}, "473": {"A": 0}, "493": {"A": 0}, "501": {"A": 0}, "512": {"A": 0}, "539": {"A": 0}, "554": {"A": 0}, "559": {"A": 0}, "583": {"A": 0}, "596": {"A": 0}, "600": {"A": 0}, "620": {"A": 0}, "639": {"A": 0}, "654": {"A": 0}, "672": {"A": 0}, "680": {"A": 0}, "691": {"A": 0}, "714": {"A": 0}, "732": {"A": 0}, "737": {"A": 0}, "751": {"A": 0}, "776": {"A": 0}, "794": {"A": 0}, "798": {"A": 0}, "818": {"A": 0}, "826": {"A": 0}, "850": {"A": 0}, "865": {"A": 0}, "873": {"A": 0}, "889": {"A": 0}, "902": {"A": 0}, "925": {"A": 0}, "940": {"A": 0}, "949": {"A": 0}, "971": {"A": 0}, "983": {"A": 0}, "993": {"A": 0}, "1016": {"A": 0}, "1025": {"A": 0}, "1048": {"A": 0}, "1064": {"A": 0}, "1070": {"A": 0}, "1090": {"A": 0}, "1096": {"A": 0}, "1110": {"A": 0}, "1137": {"A": 0}, "1144": {"A": 0}, "1163": {"A": 0}, "1178": {"A": 0}, "1189": {"A": 0}, "1212": {"A": 0}, "1223": {"A": 0}, "1234": {"A": 0}, "1255": {"A": 0}, "1265": {"A": 0}, "1282": {"A": 0}, "1295": {"A": 0}, "1306": {"A": 0}, "1328": {"A": 0}, "1346": {"A": 0}, "1353": {"A": 0}, "1373": {"A": 0}, "1386": {"A": 0}, "1405": {"A": 0}, "1415": {"A": 0}, "1434": {"A": 0}, "1452": {"A": 0}, "1469": {"A": 0}, "1479": {"A": 0}, "1485": {"A": 0}}, {"12": {"A": 6}, "25": {"A": 6}, "35": {"A": 6}, "56": {"A": 6}, "62": {"A": 6}, "77": {"A": 6}, "97": {"A": 6}, "118": {"A": 6}, "122": {"A": 6}, "137": {"A": 6}, "160": {"A": 6}, "169": {"A": 6}, "183": {"A": 6}, "203": {"A": 6}, "223": {"A": 6}, "233": {"A": 6}, "243": {"A": 6}, "263": {"A": 6}, "270": {"A": 6}, "285": {"A": 6}, "307": {"A": 6}, "316": {"A": 6}, "344": {"A": 6}, "352": {"A": 6}, "366": {"A": 6}, "377": {"A": 6}, "397": {"A": 6}, "418": {"A": 6}, "420": {"A": 6}, "439": {"A": 6}, "461": {"A": 6}, "468": {"A": 6}, "492": {"A": 6}, "495": {"A": 6}, "517": {"A": 6}, "533": {"A": 6}, "542": {"A": 6}, "560": {"A": 6}, "582": {"A": 6}, "590": {"A": 6}, "607": {"A": 6}, "626": {"A": 6}, "643": {"A": 6}, "653": {"A": 6}, "674": {"A": 6}, "685": {"A": 6}, "697": {"A": 6}, "705": {"A": 6}, "720": {"A": 6}, "742": {"A": 6}, "756": {"A": 6}, "771": {"A": 6}, "782": {"A": 6}, "801": {"A": 6}, "819": {"A": 6}, "838": {"A": 6}, "841": {"A": 6}, "866": {"A": 6}, "877": {"A": 6}, "895": {"A": 6}, "905": {"A": 6}, "927": {"A": 6}, "939": {"A": 6}, "957": {"A": 6}, "960": {"A": 6}, "986": {"A": 6}, "990": {"A": 6}, "1012": {"A": 6}, "1031": {"A": 6}, "1045": {"A": 6}, "1063": {"A": 6}, "1074": {"A": 6}, "1093": {"A": 6}, "1109": {"A": 6}, "1111": {"A": 6}, "1136": {"A": 6}, "1141": {"A": 6}, "1169": {"A": 6}, "1179": {"A": 6}, "1190": {"A": 6}, "1207": {"A": 6}, "1227": {"A": 6}, "1240": {"A": 6}, "1256": {"A": 6}, "1274": {"A": 6}, "1289": {"A": 6}, "1297": {"A": 6}, "1316": {"A": 6}, "1334": {"A": 6}, "1347": {"A": 6}, "1359": {"A": 6}, "1372": {"A": 6}, "1387": {"A": 6}, "1408": {"A": 6}, "1411": {"A": 6}, "1439": {"A": 6}, "1444": {"A": 6}, "1456": {"A": 6}, "1480": {"A": 6}, "1497": {"A": 6}}, {"7": {"A": 1}, "16": {"A": 1}, "30": {"A": 1}, "50": {"A": 1}, "72": {"A": 1}, "80": {"A": 1}, "102": {"A": 1}, "113": {"A": 1}, "125": {"A": 1}, "139": {"A": 1}, "161": {"A": 1}, "166": {"A": 1}, "185": {"A": 1}, "207": {"A": 1}, "218": {"A": 1}, "239": {"A": 1}, "246": {"A": 1}, "256": {"A": 1}, "273": {"A": 1}, "291": {"A": 1}, "306": {"A": 1}, "320": {"A": 1}, "330": {"A": 1}, "349": {"A": 1}, "373": {"A": 1}, "386": {"A": 1}, "394": {"A": 1}, "413": {"A": 1}, "428": {"A": 1}, "449": {"A": 1}, "455": {"A": 1}, "465": {"A": 1}, "485": {"A": 1}, "497": {"A": 1}, "522": {"A": 1}, "526": {"A": 1}, "546": {"A": 1}, "557": {"A": 1}, "584": {"A": 1}, "587": {"A": 1}, "602": {"A": 1}, "621": {"A": 1}, "641": {"A": 1}, "652": {"A": 1}, "671": {"A": 1}, "677": {"A": 1}, "695": {"A": 1}, "711": {"A": 1}, "728": {"A": 1}, "740": {"A": 1}, "755": {"A": 1}, "766": {"A": 1}, "792": {"A": 1}, "802": {"A": 1}, "812": {"A": 1}, "827": {"A": 1}, "853": {"A": 1}, "862": {"A": 1}, "876": {"A": 1}, "886": {"A": 1}, "911": {"A": 1}, "919": {"A": 1}, "936": {"A": 1}, "955": {"A": 1}, "962": {"A": 1}, "978": {"A": 1}, "995": {"A": 1}, "1008": {"A": 1}, "1027": {"A": 1}, "1046": {"A": 1}, "1059": {"A": 1}, "1071": {"A": 1}, "1084": {"A": 1}, "1097": {"A": 1}, "1121": {"A": 1}, "1125": {"A": 1}, "1142": {"A": 1}, "1156": {"A": 1}, "1182": {"A": 1}, "1191": {"A": 1}, "1213": {"A": 1}, "1228": {"A": 1}, "1236": {"A": 1}, "1259": {"A": 1}, "1268": {"A": 1}, "1277": {"A": 1}, "1303": {"A": 1}, "1312": {"A": 1}, "1323": {"A": 1}, "1348": {"A": 1}, "1364": {"A": 1}, "1366": {"A": 1}, "1390": {"A": 1}, "1398": {"A": 1}, "1423": {"A": 1}, "1428": {"A": 1}, "1448": {"A": 1}, "1464": {"A": 1}, "1473": {"A": 1}, "1499": {"A": 1}}, {"11": {"A": 0}, "15": {"A": 0}, "41": {"A": 0}, "53": {"A": 0}, "61": {"A": 0}, "89": {"A": 0}, "100": {"A": 0}, "111": {"A": 0}, "127": {"A": 0}, "140": {"A": 0}, "150": {"A": 0}, "174": {"A": 0}, "191": {"A": 0}, "202": {"A": 0}, "211": {"A": 0}, "235": {"A": 0}, "241": {"A": 0}, "259": {"A": 0}, "277": {"A": 0}, "287": {"A": 0}, "312": {"A": 0}, "324": {"A": 0}, "336": {"A": 0}, "345": {"A": 0}, "372": {"A": 0}, "380": {"A": 0}, "400": {"A": 0}, "417": {"A": 0}, "425": {"A": 0}, "448": {"A": 0}, "456": {"A": 0}, "467": {"A": 0}, "486": {"A": 0}, "506": {"A": 0}, "515": {"A": 0}, "527": {"A": 0}, "551": {"A": 0}, "561": {"A": 0}, "576": {"A": 0}, "592": {"A": 0}, "608": {"A": 0}, "617": {"A": 0}, "638": {"A": 0}, "647": {"A": 0}, "665": {"A": 0}, "684": {"A": 0}, "702": {"A": 0}, "716": {"A": 0}, "726": {"A": 0}, "749": {"A": 0}, "752": {"A": 0}, "772": {"A": 0}, "780": {"A": 0}, "805": {"A": 0}, "815": {"A": 0}, "830": {"A": 0}, "842": {"A": 0}, "861": {"A": 0}, "875": {"A": 0}, "892": {"A": 0}, "908": {"A": 0}, "926": {"A": 0}, "937": {"A": 0}, "954": {"A": 0}, "969": {"A": 0}, "981": {"A": 0}, "994": {"A": 0}, "1014": {"A": 0}, "1020": {"A": 0}, "1037": {"A": 0}, "1060": {"A": 0}, "1078": {"A": 0}, "1085": {"A": 0}, "1100": {"A": 0}, "1123": {"A": 0}, "1131": {"A": 0}, "1154": {"A": 0}, "1165": {"A": 0}, "1170": {"A": 0}, "1194": {"A": 0}, "1209": {"A": 0}, "1226": {"A": 0}, "1242": {"A": 0}, "1253": {"A": 0}, "1271": {"A": 0}, "1285": {"A": 0}, "1290": {"A": 0}, "1308": {"A": 0}, "1327": {"A": 0}, "1340": {"A": 0}, "1355": {"A": 0}, "1379": {"A": 0}, "1385": {"A": 0}, "1402": {"A": 0}, "1424": {"A": 0}, "1425": {"A": 0}, "1443": {"A": 0}, "1463": {"A": 0}, "1478": {"A": 0}, "1491": {"A": 0}}, {"10": {"A": 1}, "19": {"A": 1}, "37": {"A": 1}, "48": {"A": 1}, "68": {"A": 1}, "87": {"A": 1}, "103": {"A": 1}, "116": {"A": 1}, "131": {"A": 1}, "145": {"A": 1}, "162": {"A": 1}, "168": {"A": 1}, "189": {"A": 1}, "197": {"A": 1}, "215": {"A": 1}, "232": {"A": 1}, "247": {"A": 1}, "264": {"A": 1}, "279": {"A": 1}, "290": {"A": 1}, "309": {"A": 1}, "318": {"A": 1}, "333": {"A": 1}, "348": {"A": 1}, "368": {"A": 1}, "389": {"A": 1}, "398": {"A": 1}, "411": {"A": 1}, "429": {"A": 1}, "443": {"A": 1}, "450": {"A": 1}, "474": {"A": 1}, "491": {"A": 1}, "499": {"A": 1}, "516": {"A": 1}, "535": {"A": 1}, "549": {"A": 1}, "567": {"A": 1}, "581": {"A": 1}, "598": {"A": 1}, "604": {"A": 1}, "618": {"A": 1}, "635": {"A": 1}, "649": {"A": 1}, "664": {"A": 1}, "688": {"A": 1}, "703": {"A": 1}, "707": {"A": 1}, "722": {"A": 1}, "738": {"A": 1}, "750": {"A": 1}, "769": {"A": 1}, "786": {"A": 1}, "807": {"A": 1}, "813": {"A": 1}, "825": {"A": 1}, "852": {"A": 1}, "860": {"A": 1}, "879": {"A": 1}, "888": {"A": 1}, "907": {"A": 1}, "918": {"A": 1}, "942": {"A": 1}, "953": {"A": 1}, "967": {"A": 1}, "976": {"A": 1}, "1003": {"A": 1}, "1019": {"A": 1}, "1033": {"A": 1}, "1041": {"A": 1}, "1057": {"A": 1}, "1065": {"A": 1}, "1087": {"A": 1}, "1105": {"A": 1}, "1120": {"A": 1}, "1139": {"A": 1}, "1151": {"A": 1}, "1167": {"A": 1}, "1176": {"A": 1}, "1185": {"A": 1}, "1214": {"A": 1}, "1221": {"A": 1}, "1235": {"A": 1}, "1257": {"A": 1}, "1272": {"A": 1}, "1283": {"A": 1}, "1300": {"A": 1}, "1309": {"A": 1}, "1320": {"A": 1}, "1337": {"A": 1}, "1354": {"A": 1}, "1371": {"A": 1}, "1392": {"A": 1}, "1403": {"A": 1}, "1419": {"A": 1}, "1433": {"A": 1}, "1446": {"A": 1}, "1461": {"A": 1}, "1474": {"A": 1}, "1496": {"A": 1}}, {"5": {"A": 6}, "21": {"A": 6}, "44": {"A": 6}, "49": {"A": 6}, "66": {"A": 6}, "85": {"A": 6}, "93": {"A": 6}, "108": {"A": 6}, "126": {"A": 6}, "138": {"A": 6}, "156": {"A": 6}, "172": {"A": 6}, "188": {"A": 6}, "195": {"A": 6}, "224": {"A": 6}, "234": {"A": 6}, "242": {"A": 6}, "265": {"A": 6}, "284": {"A": 6}, "293": {"A": 6}, "301": {"A": 6}, "327": {"A": 6}, "340": {"A": 6}, "355": {"A": 6}, "361": {"A": 6}, "384": {"A": 6}, "391": {"A": 6}, "405": {"A": 6}, "434": {"A": 6}, "447": {"A": 6}, "459": {"A": 6}, "476": {"A": 6}, "481": {"A": 6}, "502": {"A": 6}, "519": {"A": 6}, "532": {"A": 6}, "548": {"A": 6}, "564": {"A": 6}, "577": {"A": 6}, "594": {"A": 6}, "606": {"A": 6}, "619": {"A": 6}, "632": {"A": 6}, "656": {"A": 6}, "666": {"A": 6}, "679": {"A": 6}, "696": {"A": 6}, "712": {"A": 6}, "727": {"A": 6}, "746": {"A": 6}, "754": {"A": 6}, "773": {"A": 6}, "787": {"A": 6}, "800": {"A": 6}, "816": {"A": 6}, "831": {"A": 6}, "854": {"A": 6}, "868": {"A": 6}, "871": {"A": 6}, "894": {"A": 6}, "904": {"A": 6}, "921": {"A": 6}, "935": {"A": 6}, "948": {"A": 6}, "968": {"A": 6}, "984": {"A": 6}, "997": {"A": 6}, "1015": {"A": 6}, "1026": {"A": 6}, "1036": {"A": 6}, "1050": {"A": 6}, "1076": {"A": 6}, "1086": {"A": 6}, "1098": {"A": 6}, "1113": {"A": 6}, "1133": {"A": 6}, "1147": {"A": 6}, "1159": {"A": 6}, "1181": {"A": 6}, "1198": {"A": 6}, "1206": {"A": 6}, "1219": {"A": 6}, "1239": {"A": 6}, "1250": {"A": 6}, "1269": {"A": 6}, "1276": {"A": 6}, "1292": {"A": 6}, "1307": {"A": 6}, "1329": {"A": 6}, "1342": {"A": 6}, "1351": {"A": 6}, "1369": {"A": 6}, "1384": {"A": 6}, "1396": {"A": 6}, "1414": {"A": 6}, "1436": {"A": 6}, "1440": {"A": 6}, "1462": {"A": 6}, "1477": {"A": 6}, "1494": {"A": 6}}, {"0": {"A": 6}, "17": {"A": 6}, "40": {"A": 6}, "54": {"A": 6}, "71": {"A": 6}, "75": {"A": 6}, "91": {"A": 6}, "115": {"A": 6}, "120": {"A": 6}, "144": {"A": 6}, "152": {"A": 6}, "177": {"A": 6}, "184": {"A": 6}, "208": {"A": 6}, "221": {"A": 6}, "230": {"A": 6}, "245": {"A": 6}, "262": {"A": 6}, "281": {"A": 6}, "286": {"A": 6}, "300": {"A": 6}, "325": {"A": 6}, "341": {"A": 6}, "358": {"A": 6}, "371": {"A": 6}, "375": {"A": 6}, "393": {"A": 6}, "410": {"A": 6}, "432": {"A": 6}, "435": {"A": 6}, "454": {"A": 6}, "475": {"A": 6}, "490": {"A": 6}, "500": {"A": 6}, "518": {"A": 6}, "530": {"A": 6}, "550": {"A": 6}, "566": {"A": 6}, "573": {"A": 6}, "586": {"A": 6}, "601": {"A": 6}, "629": {"A": 6}, "640": {"A": 6}, "657": {"A": 6}, "670": {"A": 6}, "686": {"A": 6}, "701": {"A": 6}, "719": {"A": 6}, "724": {"A": 6}, "748": {"A": 6}, "761": {"A": 6}, "767": {"A": 6}, "788": {"A": 6}, "797": {"A": 6}, "814": {"A": 6}, "836": {"A": 6}, "844": {"A": 6}, "858": {"A": 6}, "870": {"A": 6}, "897": {"A": 6}, "901": {"A": 6}, "916": {"A": 6}, "932": {"A": 6}, "950": {"A": 6}, "965": {"A": 6}, "987": {"A": 6}, "996": {"A": 6}, "1005": {"A": 6}, "1024": {"A": 6}, "1042": {"A": 6}, "1055": {"A": 6}, "1075": {"A": 6}, "1091": {"A": 6}, "1102": {"A": 6}, "1117": {"A": 6}, "1134": {"A": 6}, "1145": {"A": 6}, "1160": {"A": 6}, "1171": {"A": 6}, "1193": {"A": 6}, "1208": {"A": 6}, "1215": {"A": 6}, "1232": {"A": 6}, "1254": {"A": 6}, "1261": {"A": 6}, "1275": {"A": 6}, "1302": {"A": 6}, "1315": {"A": 6}, "1332": {"A": 6}, "1336": {"A": 6}, "1363": {"A": 6}, "1365": {"A": 6}, "1393": {"A": 6}, "1406": {"A": 6}, "1412": {"A": 6}, "1432": {"A": 6}, "1449": {"A": 6}, "1466": {"A": 6}, "1483": {"A": 6}, "1492": {"A": 6}}, {"4": {"A": 6}, "28": {"A": 6}, "34": {"A": 6}, "59": {"A": 6}, "67": {"A": 6}, "76": {"A": 6}, "98": {"A": 6}, "112": {"A": 6}, "129": {"A": 6}, "136": {"A": 6}, "151": {"A": 6}, "178": {"A": 6}, "192": {"A": 6}, "196": {"A": 6}, "217": {"A": 6}, "229": {"A": 6}, "251": {"A": 6}, "258": {"A": 6}, "272": {"A": 6}, "299": {"A": 6}, "302": {"A": 6}, "317": {"A": 6}, "332": {"A": 6}, "354": {"A": 6}, "365": {"A": 6}, "378": {"A": 6}, "402": {"A": 6}, "419": {"A": 6}, "433": {"A": 6}, "438": {"A": 6}, "460": {"A": 6}, "477": {"A": 6}, "494": {"A": 6}, "508": {"A": 6}, "521": {"A": 6}, "529": {"A": 6}, "541": {"A": 6}, "555": {"A": 6}, "580": {"A": 6}, "593": {"A": 6}, "605": {"A": 6}, "628": {"A": 6}, "631": {"A": 6}, "658": {"A": 6}, "667": {"A": 6}, "689": {"A": 6}, "698": {"A": 6}, "713": {"A": 6}, "730": {"A": 6}, "736": {"A": 6}, "760": {"A": 6}, "778": {"A": 6}, "793": {"A": 6}, "809": {"A": 6}, "810": {"A": 6}, "832": {"A": 6}, "851": {"A": 6}, "867": {"A": 6}, "878": {"A": 6}, "891": {"A": 6}, "909": {"A": 6}, "922": {"A": 6}, "931": {"A": 6}, "952": {"A": 6}, "966": {"A": 6}, "989": {"A": 6}, "998": {"A": 6}, "1018": {"A": 6}, "1021": {"A": 6}, "1038": {"A": 6}, "1061": {"A": 6}, "1079": {"A": 6}, "1088": {"A": 6}, "1101": {"A": 6}, "1118": {"A": 6}, "1128": {"A": 6}, "1149": {"A": 6}, "1162": {"A": 6}, "1172": {"A": 6}, "1187": {"A": 6}, "1202": {"A": 6}, "1222": {"A": 6}, "1231": {"A": 6}, "1249": {"A": 6}, "1264": {"A": 6}, "1279": {"A": 6}, "1291": {"A": 6}, "1305": {"A": 6}, "1331": {"A": 6}, "1338": {"A": 6}, "1362": {"A": 6}, "1376": {"A": 6}, "1394": {"A": 6}, "1409": {"A": 6}, "1410": {"A": 6}, "1429": {"A": 6}, "1441": {"A": 6}, "1468": {"A": 6}, "1482": {"A": 6}, "1498": {"A": 6}}, {"9": {"A": 1}, "26": {"A": 1}, "39": {"A": 1}, "57": {"A": 1}, "63": {"A": 1}, "81": {"A": 1}, "101": {"A": 1}, "106": {"A": 1}, "130": {"A": 1}, "135": {"A": 1}, "163": {"A": 1}, "165": {"A": 1}, "182": {"A": 1}, "204": {"A": 1}, "213": {"A": 1}, "231": {"A": 1}, "249": {"A": 1}, "266": {"A": 1}, "280": {"A": 1}, "298": {"A": 1}, "303": {"A": 1}, "315": {"A": 1}, "343": {"A": 1}, "353": {"A": 1}, "360": {"A": 1}, "382": {"A": 1}, "395": {"A": 1}, "408": {"A": 1}, "423": {"A": 1}, "437": {"A": 1}, "463": {"A": 1}, "479": {"A": 1}, "482": {"A": 1}, "505": {"A": 1}, "511": {"A": 1}, "536": {"A": 1}, "545": {"A": 1}, "558": {"A": 1}, "574": {"A": 1}, "585": {"A": 1}, "609": {"A": 1}, "623": {"A": 1}, "634": {"A": 1}, "651": {"A": 1}, "661": {"A": 1}, "675": {"A": 1}, "693": {"A": 1}, "708": {"A": 1}, "723": {"A": 1}, "744": {"A": 1}, "753": {"A": 1}, "774": {"A": 1}, "783": {"A": 1}, "803": {"A": 1}, "824": {"A": 1}, "835": {"A": 1}, "843": {"A": 1}, "857": {"A": 1}, "881": {"A": 1}, "885": {"A": 1}, "910": {"A": 1}, "917": {"A": 1}, "930": {"A": 1}, "951": {"A": 1}, "963": {"A": 1}, "979": {"A": 1}, "991": {"A": 1}, "1013": {"A": 1}, "1030": {"A": 1}, "1039": {"A": 1}, "1053": {"A": 1}, "1067": {"A": 1}, "1094": {"A": 1}, "1106": {"A": 1}, "1122": {"A": 1}, "1132": {"A": 1}, "1140": {"A": 1}, "1158": {"A": 1}, "1177": {"A": 1}, "1196": {"A": 1}, "1204": {"A": 1}, "1225": {"A": 1}, "1241": {"A": 1}, "1252": {"A": 1}, "1260": {"A": 1}, "1287": {"A": 1}, "1299": {"A": 1}, "1319": {"A": 1}, "1326": {"A": 1}, "1345": {"A": 1}, "1350": {"A": 1}, "1377": {"A": 1}, "1389": {"A": 1}, "1404": {"A": 1}, "1421": {"A": 1}, "1438": {"A": 1}, "1445": {"A": 1}, "1460": {"A": 1}, "1481": {"A": 1}, "1486": {"A": 1}}, {"8": {"A": 1}, "24": {"A": 1}, "42": {"A": 1}, "46": {"A": 1}, "73": {"A": 1}, "84": {"A": 1}, "92": {"A": 1}, "119": {"A": 1}, "121": {"A": 1}, "149": {"A": 1}, "164": {"A": 1}, "176": {"A": 1}, "181": {"A": 1}, "201": {"A": 1}, "222": {"A": 1}, "228": {"A": 1}, "240": {"A": 1}, "261": {"A": 1}, "276": {"A": 1}, "295": {"A": 1}, "311": {"A": 1}, "321": {"A": 1}, "342": {"A": 1}, "357": {"A": 1}, "369": {"A": 1}, "387": {"A": 1}, "399": {"A": 1}, "406": {"A": 1}, "426": {"A": 1}, "436": {"A": 1}, "464": {"A": 1}, "470": {"A": 1}, "487": {"A": 1}, "503": {"A": 1}, "523": {"A": 1}, "528": {"A": 1}, "547": {"A": 1}, "556": {"A": 1}, "572": {"A": 1}, "588": {"A": 1}, "612": {"A": 1}, "622": {"A": 1}, "642": {"A": 1}, "655": {"A": 1}, "662": {"A": 1}, "682": {"A": 1}, "690": {"A": 1}, "706": {"A": 1}, "731": {"A": 1}, "743": {"A": 1}, "759": {"A": 1}, "775": {"A": 1}, "791": {"A": 1}, "806": {"A": 1}, "823": {"A": 1}, "828": {"A": 1}, "845": {"A": 1}, "859": {"A": 1}, "884": {"A": 1}, "899": {"A": 1}, "914": {"A": 1}, "928": {"A": 1}, "941": {"A": 1}, "958": {"A": 1}, "964": {"A": 1}, "980": {"A": 1}, "1002": {"A": 1}, "1010": {"A": 1}, "1022": {"A": 1}, "1047": {"A": 1}, "1058": {"A": 1}, "1066": {"A": 1}, "1083": {"A": 1}, "1103": {"A": 1}, "1124": {"A": 1}, "1138": {"A": 1}, "1148": {"A": 1}, "1164": {"A": 1}, "1173": {"A": 1}, "1186": {"A": 1}, "1211": {"A": 1}, "1218": {"A": 1}, "1233": {"A": 1}, "1246": {"A": 1}, "1266": {"A": 1}, "1281": {"A": 1}, "1296": {"A": 1}, "1313": {"A": 1}, "1324": {"A": 1}, "1341": {"A": 1}, "1352": {"A": 1}, "1368": {"A": 1}, "1388": {"A": 1}, "1395": {"A": 1}, "1416": {"A": 1}, "1437": {"A": 1}, "1442": {"A": 1}, "1455": {"A": 1}, "1475": {"A": 1}, "1487": {"A": 1}}, {"13": {"A": 1}, "22": {"A": 1}, "33": {"A": 1}, "51": {"A": 1}, "60": {"A": 1}, "83": {"A": 1}, "90": {"A": 1}, "114": {"A": 1}, "134": {"A": 1}, "146": {"A": 1}, "158": {"A": 1}, "173": {"A": 1}, "190": {"A": 1}, "200": {"A": 1}, "220": {"A": 1}, "236": {"A": 1}, "253": {"A": 1}, "260": {"A": 1}, "271": {"A": 1}, "297": {"A": 1}, "308": {"A": 1}, "328": {"A": 1}, "338": {"A": 1}, "347": {"A": 1}, "374": {"A": 1}, "388": {"A": 1}, "396": {"A": 1}, "409": {"A": 1}, "421": {"A": 1}, "440": {"A": 1}, "453": {"A": 1}, "472": {"A": 1}, "484": {"A": 1}, "504": {"A": 1}, "524": {"A": 1}, "531": {"A": 1}, "543": {"A": 1}, "565": {"A": 1}, "570": {"A": 1}, "595": {"A": 1}, "610": {"A": 1}, "627": {"A": 1}, "633": {"A": 1}, "645": {"A": 1}, "669": {"A": 1}, "687": {"A": 1}, "694": {"A": 1}, "710": {"A": 1}, "721": {"A": 1}, "745": {"A": 1}, "762": {"A": 1}, "765": {"A": 1}, "784": {"A": 1}, "804": {"A": 1}, "821": {"A": 1}, "833": {"A": 1}, "840": {"A": 1}, "869": {"A": 1}, "882": {"A": 1}, "893": {"A": 1}, "912": {"A": 1}, "929": {"A": 1}, "943": {"A": 1}, "946": {"A": 1}, "970": {"A": 1}, "985": {"A": 1}, "1001": {"A": 1}, "1011": {"A": 1}, "1028": {"A": 1}, "1043": {"A": 1}, "1054": {"A": 1}, "1072": {"A": 1}, "1089": {"A": 1}, "1104": {"A": 1}, "1112": {"A": 1}, "1129": {"A": 1}, "1143": {"A": 1}, "1166": {"A": 1}, "1174": {"A": 1}, "1195": {"A": 1}, "1201": {"A": 1}, "1220": {"A": 1}, "1243": {"A": 1}, "1251": {"A": 1}, "1270": {"A": 1}, "1286": {"A": 1}, "1301": {"A": 1}, "1318": {"A": 1}, "1322": {"A": 1}, "1339": {"A": 1}, "1358": {"A": 1}, "1375": {"A": 1}, "1380": {"A": 1}, "1399": {"A": 1}, "1417": {"A": 1}, "1426": {"A": 1}, "1454": {"A": 1}, "1467": {"A": 1}, "1484": {"A": 1}, "1488": {"A": 1}}, {"6": {"A": 5}, "18": {"A": 5}, "31": {"A": 5}, "52": {"A": 5}, "65": {"A": 5}, "88": {"A": 5}, "96": {"A": 5}, "117": {"A": 5}, "124": {"A": 5}, "141": {"A": 5}, "159": {"A": 5}, "170": {"A": 5}, "193": {"A": 5}, "206": {"A": 5}, "216": {"A": 5}, "238": {"A": 5}, "252": {"A": 5}, "255": {"A": 5}, "282": {"A": 5}, "296": {"A": 5}, "310": {"A": 5}, "319": {"A": 5}, "339": {"A": 5}, "351": {"A": 5}, "370": {"A": 5}, "376": {"A": 5}, "390": {"A": 5}, "415": {"A": 5}, "431": {"A": 5}, "442": {"A": 5}, "451": {"A": 5}, "471": {"A": 5}, "489": {"A": 5}, "496": {"A": 5}, "520": {"A": 5}, "537": {"A": 5}, "552": {"A": 5}, "563": {"A": 5}, "578": {"A": 5}, "597": {"A": 5}, "613": {"A": 5}, "624": {"A": 5}, "644": {"A": 5}, "648": {"A": 5}, "668": {"A": 5}, "678": {"A": 5}, "699": {"A": 5}, "717": {"A": 5}, "733": {"A": 5}, "747": {"A": 5}, "757": {"A": 5}, "777": {"A": 5}, "789": {"A": 5}, "796": {"A": 5}, "817": {"A": 5}, "839": {"A": 5}, "847": {"A": 5}, "856": {"A": 5}, "883": {"A": 5}, "896": {"A": 5}, "906": {"A": 5}, "924": {"A": 5}, "938": {"A": 5}, "956": {"A": 5}, "961": {"A": 5}, "988": {"A": 5}, "999": {"A": 5}, "1017": {"A": 5}, "1034": {"A": 5}, "1040": {"A": 5}, "1052": {"A": 5}, "1077": {"A": 5}, "1081": {"A": 5}, "1107": {"A": 5}, "1119": {"A": 5}, "1135": {"A": 5}, "1152": {"A": 5}, "1161": {"A": 5}, "1184": {"A": 5}, "1199": {"A": 5}, "1203": {"A": 5}, "1224": {"A": 5}, "1238": {"A": 5}, "1248": {"A": 5}, "1267": {"A": 5}, "1284": {"A": 5}, "1304": {"A": 5}, "1314": {"A": 5}, "1333": {"A": 5}, "1344": {"A": 5}, "1357": {"A": 5}, "1378": {"A": 5}, "1383": {"A": 5}, "1397": {"A": 5}, "1413": {"A": 5}, "1427": {"A": 5}, "1450": {"A": 5}, "1457": {"A": 5}, "1472": {"A": 5}, "1493": {"A": 5}}, {"14": {"A": 1}, "20": {"A": 1}, "38": {"A": 1}, "55": {"A": 1}, "70": {"A": 1}, "78": {"A": 1}, "99": {"A": 1}, "110": {"A": 1}, "128": {"A": 1}, "143": {"A": 1}, "155": {"A": 1}, "171": {"A": 1}, "194": {"A": 1}, "209": {"A": 1}, "212": {"A": 1}, "227": {"A": 1}, "248": {"A": 1}, "267": {"A": 1}, "275": {"A": 1}, "294": {"A": 1}, "305": {"A": 1}, "323": {"A": 1}, "334": {"A": 1}, "350": {"A": 1}, "363": {"A": 1}, "381": {"A": 1}, "404": {"A": 1}, "412": {"A": 1}, "422": {"A": 1}, "441": {"A": 1}, "462": {"A": 1}, "466": {"A": 1}, "480": {"A": 1}, "509": {"A": 1}, "510": {"A": 1}, "525": {"A": 1}, "553": {"A": 1}, "569": {"A": 1}, "575": {"A": 1}, "589": {"A": 1}, "603": {"A": 1}, "615": {"A": 1}, "637": {"A": 1}, "659": {"A": 1}, "663": {"A": 1}, "683": {"A": 1}, "704": {"A": 1}, "715": {"A": 1}, "734": {"A": 1}, "741": {"A": 1}, "763": {"A": 1}, "770": {"A": 1}, "790": {"A": 1}, "795": {"A": 1}, "811": {"A": 1}, "837": {"A": 1}, "849": {"A": 1}, "864": {"A": 1}, "872": {"A": 1}, "898": {"A": 1}, "900": {"A": 1}, "915": {"A": 1}, "933": {"A": 1}, "945": {"A": 1}, "974": {"A": 1}, "975": {"A": 1}, "1004": {"A": 1}, "1006": {"A": 1}, "1023": {"A": 1}, "1049": {"A": 1}, "1056": {"A": 1}, "1068": {"A": 1}, "1092": {"A": 1}, "1099": {"A": 1}, "1115": {"A": 1}, "1127": {"A": 1}, "1146": {"A": 1}, "1168": {"A": 1}, "1180": {"A": 1}, "1188": {"A": 1}, "1200": {"A": 1}, "1217": {"A": 1}, "1230": {"A": 1}, "1247": {"A": 1}, "1273": {"A": 1}, "1288": {"A": 1}, "1298": {"A": 1}, "1311": {"A": 1}, "1330": {"A": 1}, "1349": {"A": 1}, "1361": {"A": 1}, "1374": {"A": 1}, "1381": {"A": 1}, "1400": {"A": 1}, "1420": {"A": 1}, "1435": {"A": 1}, "1453": {"A": 1}, "1458": {"A": 1}, "1470": {"A": 1}, "1490": {"A": 1}}, {"3": {"A": 6}, "29": {"A": 6}, "36": {"A": 6}, "58": {"A": 6}, "69": {"A": 6}, "82": {"A": 6}, "95": {"A": 6}, "107": {"A": 6}, "133": {"A": 6}, "148": {"A": 6}, "157": {"A": 6}, "175": {"A": 6}, "186": {"A": 6}, "205": {"A": 6}, "210": {"A": 6}, "237": {"A": 6}, "244": {"A": 6}, "268": {"A": 6}, "274": {"A": 6}, "288": {"A": 6}, "304": {"A": 6}, "326": {"A": 6}, "335": {"A": 6}, "346": {"A": 6}, "362": {"A": 6}, "379": {"A": 6}, "403": {"A": 6}, "414": {"A": 6}, "424": {"A": 6}, "446": {"A": 6}, "452": {"A": 6}, "469": {"A": 6}, "488": {"A": 6}, "498": {"A": 6}, "514": {"A": 6}, "534": {"A": 6}, "544": {"A": 6}, "562": {"A": 6}, "571": {"A": 6}, "591": {"A": 6}, "614": {"A": 6}, "625": {"A": 6}, "630": {"A": 6}, "646": {"A": 6}, "660": {"A": 6}, "681": {"A": 6}, "700": {"A": 6}, "709": {"A": 6}, "725": {"A": 6}, "739": {"A": 6}, "758": {"A": 6}, "779": {"A": 6}, "781": {"A": 6}, "799": {"A": 6}, "822": {"A": 6}, "834": {"A": 6}, "848": {"A": 6}, "863": {"A": 6}, "874": {"A": 6}, "887": {"A": 6}, "903": {"A": 6}, "920": {"A": 6}, "934": {"A": 6}, "947": {"A": 6}, "972": {"A": 6}, "982": {"A": 6}, "992": {"A": 6}, "1007": {"A": 6}, "1032": {"A": 6}, "1035": {"A": 6}, "1062": {"A": 6}, "1073": {"A": 6}, "1082": {"A": 6}, "1095": {"A": 6}, "1114": {"A": 6}, "1130": {"A": 6}, "1153": {"A": 6}, "1157": {"A": 6}, "1183": {"A": 6}, "1197": {"A": 6}, "1205": {"A": 6}, "1216": {"A": 6}, "1237": {"A": 6}, "1245": {"A": 6}, "1262": {"A": 6}, "1278": {"A": 6}, "1293": {"A": 6}, "1310": {"A": 6}, "1321": {"A": 6}, "1343": {"A": 6}, "1356": {"A": 6}, "1367": {"A": 6}, "1391": {"A": 6}, "1407": {"A": 6}, "1422": {"A": 6}, "1430": {"A": 6}, "1447": {"A": 6}, "1465": {"A": 6}, "1471": {"A": 6}, "1495": {"A": 6}}]