[{"14": {"A": 6}, "16": {"A": 6}, "35": {"A": 6}, "57": {"A": 6}, "71": {"A": 6}, "86": {"A": 6}, "103": {"A": 6}, "108": {"A": 6}, "132": {"A": 6}, "147": {"A": 6}, "152": {"A": 6}, "175": {"A": 6}, "189": {"A": 6}, "208": {"A": 6}, "223": {"A": 6}, "235": {"A": 6}, "241": {"A": 6}, "256": {"A": 6}, "275": {"A": 6}, "291": {"A": 6}, "312": {"A": 6}, "315": {"A": 6}, "334": {"A": 6}, "356": {"A": 6}, "363": {"A": 6}, "378": {"A": 6}, "397": {"A": 6}, "417": {"A": 6}, "422": {"A": 6}, "445": {"A": 6}, "461": {"A": 6}, "476": {"A": 6}, "481": {"A": 6}, "496": {"A": 6}, "516": {"A": 6}, "532": {"A": 6}, "544": {"A": 6}, "560": {"A": 6}, "578": {"A": 6}, "587": {"A": 6}, "612": {"A": 6}, "620": {"A": 6}, "633": {"A": 6}, "653": {"A": 6}, "668": {"A": 6}, "686": {"A": 6}, "691": {"A": 6}, "717": {"A": 6}, "732": {"A": 6}, "749": {"A": 6}, "751": {"A": 6}, "774": {"A": 6}, "787": {"A": 6}, "806": {"A": 6}, "811": {"A": 6}, "831": {"A": 6}, "841": {"A": 6}, "855": {"A": 6}, "873": {"A": 6}, "898": {"A": 6}, "911": {"A": 6}, "915": {"A": 6}, "936": {"A": 6}, "945": {"A": 6}, "966": {"A": 6}, "982": {"A": 6}, "993": {"A": 6}, "1012": {"A": 6}, "1026": {"A": 6}, "1046": {"A": 6}, "1061": {"A": 6}, "1067": {"A": 6}, "1094": {"A": 6}, "1095": {"A": 6}, "1110": {"A": 6}, "1126": {"A": 6}, "1141": {"A": 6}, "1166": {"A": 6}, "1177": {"A": 6}, "1193": {"A": 6}, "1200": {"A": 6}, "1215": {"A": 6}, "1244": {"A": 6}, "1247": {"A": 6}, "1264": {"A": 6}, "1276": {"A": 6}, "1290": {"A": 6}, "1312": {"A": 6}, "1324": {"A": 6}, "1341": {"A": 6}, "1364": {"A": 6}, "1374": {"A": 6}, "1383": {"A": 6}, "1406": {"A": 6}, "1424": {"A": 6}, "1427": {"A": 6}, "1448": {"A": 6}, "1460": {"A": 6}, "1482": {"A": 6}, "1485": {"A": 6}}, {"5": {"A": 3}, "15": {"A": 3}, "33": {"A": 3}, "55": {"A": 3}, "69": {"A": 3}, "80": {"A": 3}, "98": {"A": 3}, "105": {"A": 3}, "122": {"A": 3}, "135": {"A": 3}, "150": {"A": 3}, "177": {"A": 3}, "192": {"A": 3}, "204": {"A": 3}, "222": {"A": 3}, "238": {"A": 3}, "245": {"A": 3}, "265": {"A": 3}, "282": {"A": 3}, "292": {"A": 3}, "303": {"A": 3}, "318": {"A": 3}, "341": {"A": 3}, "357": {"A": 3}, "362": {"A": 3}, "380": {"A": 3}, "395": {"A": 3}, "405": {"A": 3}, "426": {"A": 3}, "435": {"A": 3}, "451": {"A": 3}, "466": {"A": 3}, "484": {"A": 3}, "507": {"A": 3}, "514": {"A": 3}, "526": {"A": 3}, "543": {"A": 3}, "567": {"A": 3}, "580": {"A": 3}, "596": {"A": 3}, "601": {"A": 3}, "625": {"A": 3}, "643": {"A": 3}, "659": {"A": 3}, "662": {"A": 3}, "685": {"A": 3}, "696": {"A": 3}, "716": {"A": 3}, "727": {"A": 3}, "736": {"A": 3}, "756": {"A": 3}, "769": {"A": 3}, "784": {"A": 3}, "799": {"A": 3}, "814": {"A": 3}, "833": {"A": 3}, "850": {"A": 3}, "863": {"A": 3}, "880": {"A": 3}, "891": {"A": 3}, "913": {"A": 3}, "928": {"A": 3}, "932": {"A": 3}, "956": {"A": 3}, "967": {"A": 3}, "978": {"A": 3}, "1000": {"A": 3}, "1013": {"A": 3}, "1024": {"A": 3}, "1044": {"A": 3}, "1063": {"A": 3}, "1077": {"A": 3}, "1086": {"A": 3}, "1102": {"A": 3}, "1111": {"A": 3}, "1130": {"A": 3}, "1142": {"A": 3}, "1168": {"A": 3}, "1184": {"A": 3}, "1185": {"A": 3}, "1213": {"A": 3}, "1225": {"A": 3}, "1235": {"A": 3}, "1259": {"A": 3}, "1274": {"A": 3}, "1280": {"A": 3}, "1295": {"A": 3}, "1316": {"A": 3}, "1323": {"A": 3}, "1342": {"A": 3}, "1352": {"A": 3}, "1371": {"A": 3}, "1389": {"A": 3}, "1402": {"A": 3}, "1412": {"A": 3}, "1439": {"A": 3}, "1450": {"A": 3}, "1461": {"A": 3}, "1472": {"A": 3}, "1492": {"A": 3}}, {"0": {"A": 2}, "19": {"A": 2}, "42": {"A": 2}, "59": {"A": 2}, "66": {"A": 2}, "84": {"A": 2}, "104": {"A": 2}, "112": {"A": 2}, "124": {"A": 2}, "148": {"A": 2}, "158": {"A": 2}, "179": {"A": 2}, "194": {"A": 2}, "195": {"A": 2}, "219": {"A": 2}, "225": {"A": 2}, "248": {"A": 2}, "258": {"A": 2}, "284": {"A": 2}, "288": {"A": 2}, "314": {"A": 2}, "316": {"A": 2}, "336": {"A": 2}, "359": {"A": 2}, "361": {"A": 2}, "383": {"A": 2}, "391": {"A": 2}, "419": {"A": 2}, "420": {"A": 2}, "439": {"A": 2}, "452": {"A": 2}, "465": {"A": 2}, "487": {"A": 2}, "497": {"A": 2}, "513": {"A": 2}, "537": {"A": 2}, "546": {"A": 2}, "557": {"A": 2}, "583": {"A": 2}, "593": {"A": 2}, "614": {"A": 2}, "629": {"A": 2}, "640": {"A": 2}, "655": {"A": 2}, "667": {"A": 2}, "682": {"A": 2}, "703": {"A": 2}, "707": {"A": 2}, "734": {"A": 2}, "739": {"A": 2}, "760": {"A": 2}, "765": {"A": 2}, "791": {"A": 2}, "803": {"A": 2}, "821": {"A": 2}, "832": {"A": 2}, "854": {"A": 2}, "856": {"A": 2}, "882": {"A": 2}, "889": {"A": 2}, "900": {"A": 2}, "923": {"A": 2}, "930": {"A": 2}, "954": {"A": 2}, "964": {"A": 2}, "977": {"A": 2}, "996": {"A": 2}, "1009": {"A": 2}, "1023": {"A": 2}, "1039": {"A": 2}, "1059": {"A": 2}, "1074": {"A": 2}, "1085": {"A": 2}, "1101": {"A": 2}, "1115": {"A": 2}, "1129": {"A": 2}, "1151": {"A": 2}, "1164": {"A": 2}, "1183": {"A": 2}, "1191": {"A": 2}, "1205": {"A": 2}, "1228": {"A": 2}, "1239": {"A": 2}, "1250": {"A": 2}, "1269": {"A": 2}, "1275": {"A": 2}, "1294": {"A": 2}, "1313": {"A": 2}, "1321": {"A": 2}, "1340": {"A": 2}, "1354": {"A": 2}, "1375": {"A": 2}, "1387": {"A": 2}, "1400": {"A": 2}, "1420": {"A": 2}, "1433": {"A": 2}, "1453": {"A": 2}, "1458": {"A": 2}, "1478": {"A": 2}, "1486": {"A": 2}}, {"10": {"A": 4}, "21": {"A": 4}, "37": {"A": 4}, "48": {"A": 4}, "67": {"A": 4}, "82": {"A": 4}, "102": {"A": 4}, "113": {"A": 4}, "125": {"A": 4}, "141": {"A": 4}, "151": {"A": 4}, "176": {"A": 4}, "187": {"A": 4}, "209": {"A": 4}, "211": {"A": 4}, "233": {"A": 4}, "243": {"A": 4}, "261": {"A": 4}, "274": {"A": 4}, "290": {"A": 4}, "305": {"A": 4}, "325": {"A": 4}, "338": {"A": 4}, "345": {"A": 4}, "366": {"A": 4}, "381": {"A": 4}, "400": {"A": 4}, "406": {"A": 4}, "434": {"A": 4}, "438": {"A": 4}, "460": {"A": 4}, "468": {"A": 4}, "490": {"A": 4}, "498": {"A": 4}, "520": {"A": 4}, "538": {"A": 4}, "550": {"A": 4}, "569": {"A": 4}, "582": {"A": 4}, "599": {"A": 4}, "605": {"A": 4}, "622": {"A": 4}, "631": {"A": 4}, "657": {"A": 4}, "660": {"A": 4}, "688": {"A": 4}, "704": {"A": 4}, "711": {"A": 4}, "720": {"A": 4}, "743": {"A": 4}, "758": {"A": 4}, "778": {"A": 4}, "785": {"A": 4}, "804": {"A": 4}, "819": {"A": 4}, "828": {"A": 4}, "848": {"A": 4}, "864": {"A": 4}, "870": {"A": 4}, "888": {"A": 4}, "903": {"A": 4}, "925": {"A": 4}, "937": {"A": 4}, "948": {"A": 4}, "970": {"A": 4}, "984": {"A": 4}, "991": {"A": 4}, "1008": {"A": 4}, "1031": {"A": 4}, "1049": {"A": 4}, "1057": {"A": 4}, "1072": {"A": 4}, "1090": {"A": 4}, "1107": {"A": 4}, "1119": {"A": 4}, "1131": {"A": 4}, "1146": {"A": 4}, "1155": {"A": 4}, "1174": {"A": 4}, "1190": {"A": 4}, "1209": {"A": 4}, "1224": {"A": 4}, "1238": {"A": 4}, "1256": {"A": 4}, "1271": {"A": 4}, "1289": {"A": 4}, "1291": {"A": 4}, "1314": {"A": 4}, "1329": {"A": 4}, "1345": {"A": 4}, "1356": {"A": 4}, "1367": {"A": 4}, "1393": {"A": 4}, "1409": {"A": 4}, "1416": {"A": 4}, "1431": {"A": 4}, "1442": {"A": 4}, "1459": {"A": 4}, "1471": {"A": 4}, "1493": {"A": 4}}, {"7": {"A": 6}, "24": {"A": 6}, "36": {"A": 6}, "47": {"A": 6}, "63": {"A": 6}, "88": {"A": 6}, "99": {"A": 6}, "119": {"A": 6}, "129": {"A": 6}, "145": {"A": 6}, "162": {"A": 6}, "166": {"A": 6}, "191": {"A": 6}, "206": {"A": 6}, "220": {"A": 6}, "226": {"A": 6}, "253": {"A": 6}, "257": {"A": 6}, "276": {"A": 6}, "289": {"A": 6}, "310": {"A": 6}, "323": {"A": 6}, "337": {"A": 6}, "351": {"A": 6}, "368": {"A": 6}, "376": {"A": 6}, "396": {"A": 6}, "407": {"A": 6}, "432": {"A": 6}, "447": {"A": 6}, "456": {"A": 6}, "475": {"A": 6}, "480": {"A": 6}, "505": {"A": 6}, "518": {"A": 6}, "533": {"A": 6}, "548": {"A": 6}, "556": {"A": 6}, "571": {"A": 6}, "598": {"A": 6}, "611": {"A": 6}, "619": {"A": 6}, "630": {"A": 6}, "646": {"A": 6}, "671": {"A": 6}, "684": {"A": 6}, "700": {"A": 6}, "708": {"A": 6}, "726": {"A": 6}, "740": {"A": 6}, "755": {"A": 6}, "779": {"A": 6}, "794": {"A": 6}, "808": {"A": 6}, "816": {"A": 6}, "839": {"A": 6}, "852": {"A": 6}, "861": {"A": 6}, "884": {"A": 6}, "885": {"A": 6}, "910": {"A": 6}, "929": {"A": 6}, "944": {"A": 6}, "952": {"A": 6}, "960": {"A": 6}, "979": {"A": 6}, "1002": {"A": 6}, "1011": {"A": 6}, "1032": {"A": 6}, "1036": {"A": 6}, "1064": {"A": 6}, "1075": {"A": 6}, "1089": {"A": 6}, "1106": {"A": 6}, "1122": {"A": 6}, "1132": {"A": 6}, "1154": {"A": 6}, "1163": {"A": 6}, "1179": {"A": 6}, "1196": {"A": 6}, "1210": {"A": 6}, "1221": {"A": 6}, "1233": {"A": 6}, "1248": {"A": 6}, "1265": {"A": 6}, "1282": {"A": 6}, "1297": {"A": 6}, "1308": {"A": 6}, "1332": {"A": 6}, "1336": {"A": 6}, "1360": {"A": 6}, "1373": {"A": 6}, "1386": {"A": 6}, "1403": {"A": 6}, "1419": {"A": 6}, "1435": {"A": 6}, "1446": {"A": 6}, "1463": {"A": 6}, "1474": {"A": 6}, "1498": {"A": 6}}, {"2": {"A": 1}, "29": {"A": 1}, "39": {"A": 1}, "45": {"A": 1}, "72": {"A": 1}, "77": {"A": 1}, "91": {"A": 1}, "115": {"A": 1}, "127": {"A": 1}, "139": {"A": 1}, "159": {"A": 1}, "171": {"A": 1}, "188": {"A": 1}, "196": {"A": 1}, "213": {"A": 1}, "236": {"A": 1}, "251": {"A": 1}, "268": {"A": 1}, "270": {"A": 1}, "286": {"A": 1}, "304": {"A": 1}, "319": {"A": 1}, "330": {"A": 1}, "354": {"A": 1}, "372": {"A": 1}, "384": {"A": 1}, "390": {"A": 1}, "409": {"A": 1}, "425": {"A": 1}, "437": {"A": 1}, "455": {"A": 1}, "470": {"A": 1}, "488": {"A": 1}, "499": {"A": 1}, "522": {"A": 1}, "529": {"A": 1}, "549": {"A": 1}, "555": {"A": 1}, "584": {"A": 1}, "589": {"A": 1}, "602": {"A": 1}, "621": {"A": 1}, "637": {"A": 1}, "654": {"A": 1}, "672": {"A": 1}, "689": {"A": 1}, "698": {"A": 1}, "719": {"A": 1}, "725": {"A": 1}, "737": {"A": 1}, "750": {"A": 1}, "777": {"A": 1}, "783": {"A": 1}, "801": {"A": 1}, "822": {"A": 1}, "829": {"A": 1}, "851": {"A": 1}, "859": {"A": 1}, "872": {"A": 1}, "890": {"A": 1}, "907": {"A": 1}, "919": {"A": 1}, "940": {"A": 1}, "946": {"A": 1}, "962": {"A": 1}, "986": {"A": 1}, "999": {"A": 1}, "1017": {"A": 1}, "1025": {"A": 1}, "1042": {"A": 1}, "1058": {"A": 1}, "1071": {"A": 1}, "1083": {"A": 1}, "1096": {"A": 1}, "1114": {"A": 1}, "1125": {"A": 1}, "1143": {"A": 1}, "1167": {"A": 1}, "1180": {"A": 1}, "1195": {"A": 1}, "1204": {"A": 1}, "1217": {"A": 1}, "1240": {"A": 1}, "1253": {"A": 1}, "1270": {"A": 1}, "1278": {"A": 1}, "1300": {"A": 1}, "1306": {"A": 1}, "1326": {"A": 1}, "1339": {"A": 1}, "1359": {"A": 1}, "1378": {"A": 1}, "1384": {"A": 1}, "1407": {"A": 1}, "1411": {"A": 1}, "1429": {"A": 1}, "1452": {"A": 1}, "1464": {"A": 1}, "1477": {"A": 1}, "1490": {"A": 1}}, {"9": {"A": 4}, "28": {"A": 4}, "34": {"A": 4}, "58": {"A": 4}, "62": {"A": 4}, "89": {"A": 4}, "93": {"A": 4}, "114": {"A": 4}, "128": {"A": 4}, "136": {"A": 4}, "164": {"A": 4}, "174": {"A": 4}, "182": {"A": 4}, "207": {"A": 4}, "216": {"A": 4}, "229": {"A": 4}, "249": {"A": 4}, "264": {"A": 4}, "271": {"A": 4}, "296": {"A": 4}, "308": {"A": 4}, "327": {"A": 4}, "340": {"A": 4}, "352": {"A": 4}, "367": {"A": 4}, "379": {"A": 4}, "404": {"A": 4}, "413": {"A": 4}, "423": {"A": 4}, "443": {"A": 4}, "464": {"A": 4}, "467": {"A": 4}, "494": {"A": 4}, "504": {"A": 4}, "515": {"A": 4}, "528": {"A": 4}, "541": {"A": 4}, "566": {"A": 4}, "573": {"A": 4}, "595": {"A": 4}, "607": {"A": 4}, "617": {"A": 4}, "641": {"A": 4}, "650": {"A": 4}, "670": {"A": 4}, "681": {"A": 4}, "690": {"A": 4}, "709": {"A": 4}, "731": {"A": 4}, "742": {"A": 4}, "752": {"A": 4}, "768": {"A": 4}, "782": {"A": 4}, "802": {"A": 4}, "815": {"A": 4}, "836": {"A": 4}, "844": {"A": 4}, "857": {"A": 4}, "879": {"A": 4}, "892": {"A": 4}, "912": {"A": 4}, "927": {"A": 4}, "933": {"A": 4}, "955": {"A": 4}, "973": {"A": 4}, "988": {"A": 4}, "997": {"A": 4}, "1006": {"A": 4}, "1020": {"A": 4}, "1043": {"A": 4}, "1050": {"A": 4}, "1065": {"A": 4}, "1087": {"A": 4}, "1098": {"A": 4}, "1124": {"A": 4}, "1135": {"A": 4}, "1148": {"A": 4}, "1159": {"A": 4}, "1175": {"A": 4}, "1194": {"A": 4}, "1206": {"A": 4}, "1222": {"A": 4}, "1234": {"A": 4}, "1252": {"A": 4}, "1272": {"A": 4}, "1285": {"A": 4}, "1298": {"A": 4}, "1318": {"A": 4}, "1322": {"A": 4}, "1335": {"A": 4}, "1351": {"A": 4}, "1366": {"A": 4}, "1394": {"A": 4}, "1404": {"A": 4}, "1423": {"A": 4}, "1436": {"A": 4}, "1447": {"A": 4}, "1466": {"A": 4}, "1480": {"A": 4}, "1489": {"A": 4}}, {"6": {"A": 0}, "27": {"A": 0}, "31": {"A": 0}, "51": {"A": 0}, "74": {"A": 0}, "85": {"A": 0}, "96": {"A": 0}, "107": {"A": 0}, "126": {"A": 0}, "140": {"A": 0}, "163": {"A": 0}, "167": {"A": 0}, "184": {"A": 0}, "197": {"A": 0}, "221": {"A": 0}, "239": {"A": 0}, "244": {"A": 0}, "260": {"A": 0}, "277": {"A": 0}, "295": {"A": 0}, "300": {"A": 0}, "329": {"A": 0}, "333": {"A": 0}, "358": {"A": 0}, "374": {"A": 0}, "382": {"A": 0}, "399": {"A": 0}, "411": {"A": 0}, "427": {"A": 0}, "440": {"A": 0}, "457": {"A": 0}, "473": {"A": 0}, "483": {"A": 0}, "500": {"A": 0}, "521": {"A": 0}, "535": {"A": 0}, "552": {"A": 0}, "563": {"A": 0}, "576": {"A": 0}, "591": {"A": 0}, "608": {"A": 0}, "615": {"A": 0}, "642": {"A": 0}, "652": {"A": 0}, "665": {"A": 0}, "678": {"A": 0}, "699": {"A": 0}, "706": {"A": 0}, "721": {"A": 0}, "738": {"A": 0}, "759": {"A": 0}, "766": {"A": 0}, "786": {"A": 0}, "795": {"A": 0}, "810": {"A": 0}, "837": {"A": 0}, "845": {"A": 0}, "868": {"A": 0}, "875": {"A": 0}, "895": {"A": 0}, "904": {"A": 0}, "922": {"A": 0}, "942": {"A": 0}, "957": {"A": 0}, "974": {"A": 0}, "981": {"A": 0}, "998": {"A": 0}, "1014": {"A": 0}, "1029": {"A": 0}, "1047": {"A": 0}, "1055": {"A": 0}, "1068": {"A": 0}, "1084": {"A": 0}, "1099": {"A": 0}, "1113": {"A": 0}, "1127": {"A": 0}, "1147": {"A": 0}, "1165": {"A": 0}, "1170": {"A": 0}, "1197": {"A": 0}, "1208": {"A": 0}, "1220": {"A": 0}, "1241": {"A": 0}, "1254": {"A": 0}, "1261": {"A": 0}, "1277": {"A": 0}, "1292": {"A": 0}, "1311": {"A": 0}, "1334": {"A": 0}, "1348": {"A": 0}, "1353": {"A": 0}, "1365": {"A": 0}, "1390": {"A": 0}, "1408": {"A": 0}, "1410": {"A": 0}, "1430": {"A": 0}, "1451": {"A": 0}, "1457": {"A": 0}, "1476": {"A": 0}, "1496": {"A": 0}}, {"4": {"A": 1}, "17": {"A": 1}, "30": {"A": 1}, "50": {"A": 1}, "64": {"A": 1}, "76": {"A": 1}, "94": {"A": 1}, "116": {"A": 1}, "130": {"A": 1}, "149": {"A": 1}, "157": {"A": 1}, "172": {"A": 1}, "193": {"A": 1}, "200": {"A": 1}, "215": {"A": 1}, "228": {"A": 1}, "240": {"A": 1}, "263": {"A": 1}, "283": {"A": 1}, "285": {"A": 1}, "313": {"A": 1}, "328": {"A": 1}, "342": {"A": 1}, "353": {"A": 1}, "371": {"A": 1}, "377": {"A": 1}, "402": {"A": 1}, "418": {"A": 1}, "428": {"A": 1}, "436": {"A": 1}, "458": {"A": 1}, "469": {"A": 1}, "486": {"A": 1}, "506": {"A": 1}, "510": {"A": 1}, "539": {"A": 1}, "545": {"A": 1}, "558": {"A": 1}, "581": {"A": 1}, "594": {"A": 1}, "604": {"A": 1}, "624": {"A": 1}, "635": {"A": 1}, "656": {"A": 1}, "661": {"A": 1}, "679": {"A": 1}, "695": {"A": 1}, "718": {"A": 1}, "729": {"A": 1}, "746": {"A": 1}, "757": {"A": 1}, "771": {"A": 1}, "788": {"A": 1}, "809": {"A": 1}, "820": {"A": 1}, "835": {"A": 1}, "847": {"A": 1}, "865": {"A": 1}, "877": {"A": 1}, "893": {"A": 1}, "905": {"A": 1}, "920": {"A": 1}, "943": {"A": 1}, "958": {"A": 1}, "968": {"A": 1}, "985": {"A": 1}, "1001": {"A": 1}, "1019": {"A": 1}, "1028": {"A": 1}, "1035": {"A": 1}, "1053": {"A": 1}, "1070": {"A": 1}, "1088": {"A": 1}, "1100": {"A": 1}, "1120": {"A": 1}, "1138": {"A": 1}, "1152": {"A": 1}, "1160": {"A": 1}, "1172": {"A": 1}, "1192": {"A": 1}, "1203": {"A": 1}, "1216": {"A": 1}, "1236": {"A": 1}, "1255": {"A": 1}, "1267": {"A": 1}, "1286": {"A": 1}, "1304": {"A": 1}, "1310": {"A": 1}, "1328": {"A": 1}, "1349": {"A": 1}, "1358": {"A": 1}, "1376": {"A": 1}, "1381": {"A": 1}, "1395": {"A": 1}, "1414": {"A": 1}, "1426": {"A": 1}, "1444": {"A": 1}, "1469": {"A": 1}, "1475": {"A": 1}, "1491": {"A": 1}}, {"1": {"A": 1}, "25": {"A": 1}, "44": {"A": 1}, "46": {"A": 1}, "65": {"A": 1}, "81": {"A": 1}, "95": {"A": 1}, "111": {"A": 1}, "121": {"A": 1}, "144": {"A": 1}, "153": {"A": 1}, "178": {"A": 1}, "186": {"A": 1}, "201": {"A": 1}, "214": {"A": 1}, "230": {"A": 1}, "247": {"A": 1}, "259": {"A": 1}, "273": {"A": 1}, "294": {"A": 1}, "306": {"A": 1}, "317": {"A": 1}, "331": {"A": 1}, "355": {"A": 1}, "369": {"A": 1}, "386": {"A": 1}, "393": {"A": 1}, "415": {"A": 1}, "421": {"A": 1}, "444": {"A": 1}, "463": {"A": 1}, "471": {"A": 1}, "482": {"A": 1}, "495": {"A": 1}, "517": {"A": 1}, "536": {"A": 1}, "551": {"A": 1}, "568": {"A": 1}, "570": {"A": 1}, "592": {"A": 1}, "610": {"A": 1}, "616": {"A": 1}, "639": {"A": 1}, "645": {"A": 1}, "669": {"A": 1}, "680": {"A": 1}, "692": {"A": 1}, "714": {"A": 1}, "724": {"A": 1}, "747": {"A": 1}, "762": {"A": 1}, "770": {"A": 1}, "793": {"A": 1}, "800": {"A": 1}, "824": {"A": 1}, "825": {"A": 1}, "842": {"A": 1}, "860": {"A": 1}, "876": {"A": 1}, "897": {"A": 1}, "914": {"A": 1}, "916": {"A": 1}, "938": {"A": 1}, "959": {"A": 1}, "963": {"A": 1}, "989": {"A": 1}, "995": {"A": 1}, "1005": {"A": 1}, "1030": {"A": 1}, "1048": {"A": 1}, "1060": {"A": 1}, "1078": {"A": 1}, "1091": {"A": 1}, "1108": {"A": 1}, "1121": {"A": 1}, "1136": {"A": 1}, "1145": {"A": 1}, "1156": {"A": 1}, "1178": {"A": 1}, "1199": {"A": 1}, "1201": {"A": 1}, "1226": {"A": 1}, "1242": {"A": 1}, "1249": {"A": 1}, "1268": {"A": 1}, "1279": {"A": 1}, "1293": {"A": 1}, "1315": {"A": 1}, "1333": {"A": 1}, "1346": {"A": 1}, "1362": {"A": 1}, "1368": {"A": 1}, "1385": {"A": 1}, "1399": {"A": 1}, "1417": {"A": 1}, "1438": {"A": 1}, "1443": {"A": 1}, "1455": {"A": 1}, "1470": {"A": 1}, "1488": {"A": 1}}, {"12": {"A": 1}, "23": {"A": 1}, "40": {"A": 1}, "54": {"A": 1}, "61": {"A": 1}, "83": {"A": 1}, "92": {"A": 1}, "117": {"A": 1}, "133": {"A": 1}, "138": {"A": 1}, "156": {"A": 1}, "170": {"A": 1}, "180": {"A": 1}, "198": {"A": 1}, "212": {"A": 1}, "237": {"A": 1}, "250": {"A": 1}, "266": {"A": 1}, "280": {"A": 1}, "298": {"A": 1}, "301": {"A": 1}, "324": {"A": 1}, "339": {"A": 1}, "347": {"A": 1}, "364": {"A": 1}, "389": {"A": 1}, "401": {"A": 1}, "414": {"A": 1}, "430": {"A": 1}, "441": {"A": 1}, "462": {"A": 1}, "472": {"A": 1}, "489": {"A": 1}, "501": {"A": 1}, "524": {"A": 1}, "530": {"A": 1}, "540": {"A": 1}, "565": {"A": 1}, "574": {"A": 1}, "585": {"A": 1}, "603": {"A": 1}, "627": {"A": 1}, "644": {"A": 1}, "651": {"A": 1}, "663": {"A": 1}, "675": {"A": 1}, "702": {"A": 1}, "715": {"A": 1}, "730": {"A": 1}, "748": {"A": 1}, "764": {"A": 1}, "776": {"A": 1}, "780": {"A": 1}, "798": {"A": 1}, "823": {"A": 1}, "834": {"A": 1}, "849": {"A": 1}, "858": {"A": 1}, "871": {"A": 1}, "894": {"A": 1}, "908": {"A": 1}, "926": {"A": 1}, "941": {"A": 1}, "953": {"A": 1}, "971": {"A": 1}, "983": {"A": 1}, "1004": {"A": 1}, "1015": {"A": 1}, "1034": {"A": 1}, "1038": {"A": 1}, "1056": {"A": 1}, "1076": {"A": 1}, "1093": {"A": 1}, "1104": {"A": 1}, "1112": {"A": 1}, "1133": {"A": 1}, "1153": {"A": 1}, "1157": {"A": 1}, "1171": {"A": 1}, "1188": {"A": 1}, "1207": {"A": 1}, "1229": {"A": 1}, "1232": {"A": 1}, "1257": {"A": 1}, "1260": {"A": 1}, "1287": {"A": 1}, "1302": {"A": 1}, "1319": {"A": 1}, "1330": {"A": 1}, "1347": {"A": 1}, "1357": {"A": 1}, "1370": {"A": 1}, "1391": {"A": 1}, "1398": {"A": 1}, "1418": {"A": 1}, "1428": {"A": 1}, "1441": {"A": 1}, "1467": {"A": 1}, "1473": {"A": 1}, "1494": {"A": 1}}, {"3": {"A": 4}, "18": {"A": 4}, "38": {"A": 4}, "53": {"A": 4}, "73": {"A": 4}, "75": {"A": 4}, "90": {"A": 4}, "118": {"A": 4}, "131": {"A": 4}, "142": {"A": 4}, "155": {"A": 4}, "169": {"A": 4}, "183": {"A": 4}, "203": {"A": 4}, "218": {"A": 4}, "231": {"A": 4}, "254": {"A": 4}, "255": {"A": 4}, "278": {"A": 4}, "299": {"A": 4}, "309": {"A": 4}, "326": {"A": 4}, "335": {"A": 4}, "348": {"A": 4}, "370": {"A": 4}, "387": {"A": 4}, "403": {"A": 4}, "416": {"A": 4}, "433": {"A": 4}, "446": {"A": 4}, "454": {"A": 4}, "479": {"A": 4}, "492": {"A": 4}, "509": {"A": 4}, "519": {"A": 4}, "531": {"A": 4}, "547": {"A": 4}, "561": {"A": 4}, "575": {"A": 4}, "590": {"A": 4}, "600": {"A": 4}, "626": {"A": 4}, "634": {"A": 4}, "648": {"A": 4}, "664": {"A": 4}, "677": {"A": 4}, "697": {"A": 4}, "710": {"A": 4}, "733": {"A": 4}, "745": {"A": 4}, "763": {"A": 4}, "767": {"A": 4}, "781": {"A": 4}, "807": {"A": 4}, "818": {"A": 4}, "830": {"A": 4}, "853": {"A": 4}, "869": {"A": 4}, "874": {"A": 4}, "896": {"A": 4}, "902": {"A": 4}, "917": {"A": 4}, "934": {"A": 4}, "950": {"A": 4}, "969": {"A": 4}, "980": {"A": 4}, "990": {"A": 4}, "1016": {"A": 4}, "1033": {"A": 4}, "1041": {"A": 4}, "1051": {"A": 4}, "1069": {"A": 4}, "1092": {"A": 4}, "1097": {"A": 4}, "1116": {"A": 4}, "1139": {"A": 4}, "1150": {"A": 4}, "1161": {"A": 4}, "1181": {"A": 4}, "1186": {"A": 4}, "1212": {"A": 4}, "1227": {"A": 4}, "1243": {"A": 4}, "1246": {"A": 4}, "1262": {"A": 4}, "1283": {"A": 4}, "1296": {"A": 4}, "1309": {"A": 4}, "1327": {"A": 4}, "1344": {"A": 4}, "1350": {"A": 4}, "1377": {"A": 4}, "1388": {"A": 4}, "1396": {"A": 4}, "1421": {"A": 4}, "1425": {"A": 4}, "1449": {"A": 4}, "1462": {"A": 4}, "1481": {"A": 4}, "1499": {"A": 4}}, {"8": {"A": 6}, "20": {"A": 6}, "41": {"A": 6}, "49": {"A": 6}, "68": {"A": 6}, "87": {"A": 6}, "97": {"A": 6}, "109": {"A": 6}, "134": {"A": 6}, "137": {"A": 6}, "154": {"A": 6}, "165": {"A": 6}, "185": {"A": 6}, "199": {"A": 6}, "224": {"A": 6}, "234": {"A": 6}, "252": {"A": 6}, "269": {"A": 6}, "279": {"A": 6}, "297": {"A": 6}, "302": {"A": 6}, "321": {"A": 6}, "344": {"A": 6}, "346": {"A": 6}, "373": {"A": 6}, "385": {"A": 6}, "394": {"A": 6}, "412": {"A": 6}, "429": {"A": 6}, "442": {"A": 6}, "450": {"A": 6}, "478": {"A": 6}, "493": {"A": 6}, "502": {"A": 6}, "512": {"A": 6}, "527": {"A": 6}, "554": {"A": 6}, "562": {"A": 6}, "579": {"A": 6}, "586": {"A": 6}, "606": {"A": 6}, "623": {"A": 6}, "632": {"A": 6}, "658": {"A": 6}, "673": {"A": 6}, "683": {"A": 6}, "701": {"A": 6}, "712": {"A": 6}, "728": {"A": 6}, "735": {"A": 6}, "753": {"A": 6}, "772": {"A": 6}, "792": {"A": 6}, "796": {"A": 6}, "813": {"A": 6}, "838": {"A": 6}, "843": {"A": 6}, "867": {"A": 6}, "881": {"A": 6}, "886": {"A": 6}, "901": {"A": 6}, "924": {"A": 6}, "935": {"A": 6}, "949": {"A": 6}, "965": {"A": 6}, "976": {"A": 6}, "994": {"A": 6}, "1007": {"A": 6}, "1027": {"A": 6}, "1037": {"A": 6}, "1054": {"A": 6}, "1079": {"A": 6}, "1080": {"A": 6}, "1103": {"A": 6}, "1118": {"A": 6}, "1137": {"A": 6}, "1140": {"A": 6}, "1162": {"A": 6}, "1182": {"A": 6}, "1187": {"A": 6}, "1202": {"A": 6}, "1218": {"A": 6}, "1237": {"A": 6}, "1251": {"A": 6}, "1266": {"A": 6}, "1284": {"A": 6}, "1303": {"A": 6}, "1317": {"A": 6}, "1320": {"A": 6}, "1343": {"A": 6}, "1363": {"A": 6}, "1379": {"A": 6}, "1382": {"A": 6}, "1397": {"A": 6}, "1413": {"A": 6}, "1434": {"A": 6}, "1440": {"A": 6}, "1468": {"A": 6}, "1483": {"A": 6}, "1487": {"A": 6}}, {"11": {"A": 3}, "26": {"A": 3}, "32": {"A": 3}, "56": {"A": 3}, "60": {"A": 3}, "79": {"A": 3}, "100": {"A": 3}, "110": {"A": 3}, "120": {"A": 3}, "146": {"A": 3}, "161": {"A": 3}, "173": {"A": 3}, "181": {"A": 3}, "205": {"A": 3}, "210": {"A": 3}, "232": {"A": 3}, "242": {"A": 3}, "267": {"A": 3}, "281": {"A": 3}, "293": {"A": 3}, "307": {"A": 3}, "320": {"A": 3}, "343": {"A": 3}, "350": {"A": 3}, "365": {"A": 3}, "388": {"A": 3}, "398": {"A": 3}, "408": {"A": 3}, "431": {"A": 3}, "449": {"A": 3}, "459": {"A": 3}, "474": {"A": 3}, "491": {"A": 3}, "508": {"A": 3}, "511": {"A": 3}, "534": {"A": 3}, "553": {"A": 3}, "564": {"A": 3}, "577": {"A": 3}, "597": {"A": 3}, "609": {"A": 3}, "618": {"A": 3}, "636": {"A": 3}, "649": {"A": 3}, "666": {"A": 3}, "676": {"A": 3}, "693": {"A": 3}, "713": {"A": 3}, "722": {"A": 3}, "744": {"A": 3}, "754": {"A": 3}, "775": {"A": 3}, "789": {"A": 3}, "805": {"A": 3}, "817": {"A": 3}, "827": {"A": 3}, "846": {"A": 3}, "866": {"A": 3}, "878": {"A": 3}, "899": {"A": 3}, "909": {"A": 3}, "918": {"A": 3}, "939": {"A": 3}, "951": {"A": 3}, "972": {"A": 3}, "975": {"A": 3}, "1003": {"A": 3}, "1018": {"A": 3}, "1022": {"A": 3}, "1040": {"A": 3}, "1062": {"A": 3}, "1066": {"A": 3}, "1081": {"A": 3}, "1105": {"A": 3}, "1117": {"A": 3}, "1128": {"A": 3}, "1149": {"A": 3}, "1169": {"A": 3}, "1173": {"A": 3}, "1189": {"A": 3}, "1211": {"A": 3}, "1219": {"A": 3}, "1231": {"A": 3}, "1258": {"A": 3}, "1263": {"A": 3}, "1288": {"A": 3}, "1299": {"A": 3}, "1305": {"A": 3}, "1331": {"A": 3}, "1337": {"A": 3}, "1361": {"A": 3}, "1372": {"A": 3}, "1380": {"A": 3}, "1401": {"A": 3}, "1422": {"A": 3}, "1432": {"A": 3}, "1445": {"A": 3}, "1465": {"A": 3}, "1484": {"A": 3}, "1497": {"A": 3}}, {"13": {"A": 3}, "22": {"A": 3}, "43": {"A": 3}, "52": {"A": 3}, "70": {"A": 3}, "78": {"A": 3}, "101": {"A": 3}, "106": {"A": 3}, "123": {"A": 3}, "143": {"A": 3}, "160": {"A": 3}, "168": {"A": 3}, "190": {"A": 3}, "202": {"A": 3}, "217": {"A": 3}, "227": {"A": 3}, "246": {"A": 3}, "262": {"A": 3}, "272": {"A": 3}, "287": {"A": 3}, "311": {"A": 3}, "322": {"A": 3}, "332": {"A": 3}, "349": {"A": 3}, "360": {"A": 3}, "375": {"A": 3}, "392": {"A": 3}, "410": {"A": 3}, "424": {"A": 3}, "448": {"A": 3}, "453": {"A": 3}, "477": {"A": 3}, "485": {"A": 3}, "503": {"A": 3}, "523": {"A": 3}, "525": {"A": 3}, "542": {"A": 3}, "559": {"A": 3}, "572": {"A": 3}, "588": {"A": 3}, "613": {"A": 3}, "628": {"A": 3}, "638": {"A": 3}, "647": {"A": 3}, "674": {"A": 3}, "687": {"A": 3}, "694": {"A": 3}, "705": {"A": 3}, "723": {"A": 3}, "741": {"A": 3}, "761": {"A": 3}, "773": {"A": 3}, "790": {"A": 3}, "797": {"A": 3}, "812": {"A": 3}, "826": {"A": 3}, "840": {"A": 3}, "862": {"A": 3}, "883": {"A": 3}, "887": {"A": 3}, "906": {"A": 3}, "921": {"A": 3}, "931": {"A": 3}, "947": {"A": 3}, "961": {"A": 3}, "987": {"A": 3}, "992": {"A": 3}, "1010": {"A": 3}, "1021": {"A": 3}, "1045": {"A": 3}, "1052": {"A": 3}, "1073": {"A": 3}, "1082": {"A": 3}, "1109": {"A": 3}, "1123": {"A": 3}, "1134": {"A": 3}, "1144": {"A": 3}, "1158": {"A": 3}, "1176": {"A": 3}, "1198": {"A": 3}, "1214": {"A": 3}, "1223": {"A": 3}, "1230": {"A": 3}, "1245": {"A": 3}, "1273": {"A": 3}, "1281": {"A": 3}, "1301": {"A": 3}, "1307": {"A": 3}, "1325": {"A": 3}, "1338": {"A": 3}, "1355": {"A": 3}, "1369": {"A": 3}, "1392": {"A": 3}, "1405": {"A": 3}, "1415": {"A": 3}, "1437": {"A": 3}, "1454": {"A": 3}, "1456": {"A": 3}, "1479": {"A": 3}, "1495": {"A": 3}}]