[{"0": [{"A": 2}, {"A": 4}, {"A": 0}, {"A": 4}, {"A": 2}, {"A": 5}, {"A": 6}, {"A": 6}, {"A": 0}, {"A": 6}, {"A": 0}, {"A": 4}, {"A": 0}, {"A": 5}, {"A": 3}, {"A": 5}, {"A": 0}, {"A": 3}, {"A": 2}, {"A": 3}, {"A": 5}, {"A": 3}, {"A": 4}, {"A": 3}, {"A": 5}, {"A": 6}, {"A": 2}, {"A": 2}, {"A": 1}, {"A": 4}, {"A": 1}, {"A": 4}, {"A": 3}, {"A": 6}, {"A": 1}, {"A": 2}, {"A": 1}, {"A": 3}, {"A": 1}, {"A": 3}, {"A": 5}, {"A": 6}, {"A": 4}, {"A": 1}, {"A": 6}, {"A": 4}, {"A": 1}, {"A": 0}, {"A": 3}, {"A": 4}]}, {"1": [{"A": 3}, {"A": 4}, {"A": 3}, {"A": 4}, {"A": 4}, {"A": 4}, {"A": 4}, {"A": 4}, {"A": 4}, {"A": 4}, {"A": 4}, {"A": 4}, {"A": 4}, {"A": 4}, {"A": 4}, {"A": 4}, {"A": 4}, {"A": 4}, {"A": 4}, {"A": 4}, {"A": 4}, {"A": 4}, {"A": 4}, {"A": 4}, {"A": 4}, {"A": 4}, {"A": 4}, {"A": 4}, {"A": 4}, {"A": 4}, {"A": 4}, {"A": 4}, {"A": 4}, {"A": 4}, {"A": 4}, {"A": 4}, {"A": 4}, {"A": 4}, {"A": 4}, {"A": 4}, {"A": 4}, {"A": 4}, {"A": 4}, {"A": 4}, {"A": 6}, {"A": 4}, {"A": 4}, {"A": 4}, {"A": 4}, {"A": 4}]}, {"2": [{"A": 2}, {"A": 4}, {"A": 2}, {"A": 2}, {"A": 4}, {"A": 4}, {"A": 4}, {"A": 4}, {"A": 4}, {"A": 4}, {"A": 4}, {"A": 4}, {"A": 4}, {"A": 2}, {"A": 4}, {"A": 4}, {"A": 4}, {"A": 4}, {"A": 4}, {"A": 4}, {"A": 4}, {"A": 4}, {"A": 4}, {"A": 4}, {"A": 4}, {"A": 4}, {"A": 4}, {"A": 4}, {"A": 4}, {"A": 4}, {"A": 4}, {"A": 4}, {"A": 4}, {"A": 4}, {"A": 4}, {"A": 4}, {"A": 4}, {"A": 4}, {"A": 4}, {"A": 4}, {"A": 4}, {"A": 4}, {"A": 4}, {"A": 4}, {"A": 4}, {"A": 4}, {"A": 4}, {"A": 4}, {"A": 4}, {"A": 4}]}, {"3": [{"A": 2}, {"A": 4}, {"A": 2}, {"A": 4}, {"A": 4}, {"A": 2}, {"A": 2}, {"A": 4}, {"A": 4}, {"A": 4}, {"A": 2}, {"A": 2}, {"A": 4}, {"A": 4}, {"A": 4}, {"A": 2}, {"A": 2}, {"A": 2}, {"A": 2}, {"A": 4}, {"A": 2}, {"A": 4}, {"A": 4}, {"A": 4}, {"A": 2}, {"A": 4}, {"A": 2}, {"A": 2}, {"A": 4}, {"A": 2}, {"A": 2}, {"A": 2}, {"A": 2}, {"A": 2}, {"A": 4}, {"A": 4}, {"A": 4}, {"A": 2}, {"A": 2}, {"A": 2}, {"A": 4}, {"A": 4}, {"A": 4}, {"A": 4}, {"A": 4}, {"A": 2}, {"A": 2}, {"A": 2}, {"A": 4}, {"A": 2}]}, {"4": [{"A": 2}, {"A": 4}, {"A": 4}, {"A": 4}, {"A": 4}, {"A": 4}, {"A": 4}, {"A": 4}, {"A": 4}, {"A": 4}, {"A": 4}, {"A": 4}, {"A": 4}, {"A": 4}, {"A": 4}, {"A": 4}, {"A": 4}, {"A": 4}, {"A": 4}, {"A": 4}, {"A": 4}, {"A": 4}, {"A": 4}, {"A": 4}, {"A": 4}, {"A": 4}, {"A": 4}, {"A": 4}, {"A": 4}, {"A": 4}, {"A": 4}, {"A": 4}, {"A": 4}, {"A": 4}, {"A": 4}, {"A": 4}, {"A": 4}, {"A": 4}, {"A": 4}, {"A": 4}, {"A": 4}, {"A": 4}, {"A": 4}, {"A": 4}, {"A": 4}, {"A": 4}, {"A": 4}, {"A": 4}, {"A": 4}, {"A": 4}]}, {"5": [{"A": 1}, {"A": 3}, {"A": 1}, {"A": 3}, {"A": 1}, {"A": 1}, {"A": 3}, {"A": 1}, {"A": 3}, {"A": 1}, {"A": 1}, {"A": 3}, {"A": 3}, {"A": 3}, {"A": 1}, {"A": 3}, {"A": 3}, {"A": 1}, {"A": 3}, {"A": 3}, {"A": 1}, {"A": 3}, {"A": 3}, {"A": 3}, {"A": 1}, {"A": 3}, {"A": 3}, {"A": 1}, {"A": 1}, {"A": 1}, {"A": 3}, {"A": 3}, {"A": 1}, {"A": 1}, {"A": 3}, {"A": 3}, {"A": 1}, {"A": 3}, {"A": 3}, {"A": 3}, {"A": 3}, {"A": 3}, {"A": 3}, {"A": 3}, {"A": 3}, {"A": 3}, {"A": 3}, {"A": 3}, {"A": 1}, {"A": 3}]}, {"6": [{"A": 3}, {"A": 3}, {"A": 3}, {"A": 3}, {"A": 3}, {"A": 3}, {"A": 3}, {"A": 3}, {"A": 3}, {"A": 3}, {"A": 3}, {"A": 3}, {"A": 3}, {"A": 3}, {"A": 3}, {"A": 3}, {"A": 3}, {"A": 3}, {"A": 3}, {"A": 3}, {"A": 3}, {"A": 3}, {"A": 3}, {"A": 3}, {"A": 3}, {"A": 3}, {"A": 3}, {"A": 3}, {"A": 3}, {"A": 3}, {"A": 3}, {"A": 3}, {"A": 3}, {"A": 3}, {"A": 3}, {"A": 3}, {"A": 3}, {"A": 3}, {"A": 3}, {"A": 3}, {"A": 3}, {"A": 3}, {"A": 3}, {"A": 3}, {"A": 3}, {"A": 3}, {"A": 3}, {"A": 3}, {"A": 3}, {"A": 3}]}, {"7": [{"A": 2}, {"A": 2}, {"A": 2}, {"A": 2}, {"A": 2}, {"A": 2}, {"A": 2}, {"A": 2}, {"A": 2}, {"A": 2}, {"A": 2}, {"A": 2}, {"A": 2}, {"A": 2}, {"A": 2}, {"A": 2}, {"A": 2}, {"A": 2}, {"A": 2}, {"A": 2}, {"A": 2}, {"A": 2}, {"A": 2}, {"A": 2}, {"A": 2}, {"A": 2}, {"A": 2}, {"A": 2}, {"A": 2}, {"A": 2}, {"A": 2}, {"A": 2}, {"A": 2}, {"A": 2}, {"A": 2}, {"A": 2}, {"A": 2}, {"A": 2}, {"A": 2}, {"A": 2}, {"A": 2}, {"A": 2}, {"A": 2}, {"A": 2}, {"A": 2}, {"A": 2}, {"A": 2}, {"A": 2}, {"A": 2}, {"A": 2}]}, {"8": [{"A": 3}, {"A": 3}, {"A": 3}, {"A": 3}, {"A": 3}, {"A": 3}, {"A": 1}, {"A": 3}, {"A": 3}, {"A": 1}, {"A": 3}, {"A": 3}, {"A": 3}, {"A": 1}, {"A": 3}, {"A": 3}, {"A": 3}, {"A": 3}, {"A": 1}, {"A": 3}, {"A": 1}, {"A": 3}, {"A": 3}, {"A": 1}, {"A": 3}, {"A": 3}, {"A": 1}, {"A": 3}, {"A": 3}, {"A": 3}, {"A": 1}, {"A": 1}, {"A": 3}, {"A": 3}, {"A": 3}, {"A": 3}, {"A": 3}, {"A": 1}, {"A": 3}, {"A": 1}, {"A": 1}, {"A": 1}, {"A": 3}, {"A": 1}, {"A": 1}, {"A": 3}, {"A": 3}, {"A": 1}, {"A": 3}, {"A": 3}]}, {"9": [{"A": 3}, {"A": 3}, {"A": 3}, {"A": 1}, {"A": 3}, {"A": 1}, {"A": 3}, {"A": 3}, {"A": 3}, {"A": 3}, {"A": 3}, {"A": 3}, {"A": 3}, {"A": 3}, {"A": 3}, {"A": 3}, {"A": 1}, {"A": 3}, {"A": 3}, {"A": 3}, {"A": 3}, {"A": 3}, {"A": 1}, {"A": 1}, {"A": 3}, {"A": 3}, {"A": 1}, {"A": 3}, {"A": 3}, {"A": 3}, {"A": 3}, {"A": 1}, {"A": 3}, {"A": 3}, {"A": 3}, {"A": 3}, {"A": 3}, {"A": 1}, {"A": 3}, {"A": 3}, {"A": 3}, {"A": 1}, {"A": 1}, {"A": 3}, {"A": 3}, {"A": 1}, {"A": 3}, {"A": 1}, {"A": 3}, {"A": 1}]}, {"10": [{"A": 4}, {"A": 4}, {"A": 4}, {"A": 4}, {"A": 4}, {"A": 4}, {"A": 4}, {"A": 4}, {"A": 4}, {"A": 4}, {"A": 4}, {"A": 1}, {"A": 4}, {"A": 4}, {"A": 4}, {"A": 4}, {"A": 4}, {"A": 4}, {"A": 4}, {"A": 4}, {"A": 4}, {"A": 4}, {"A": 4}, {"A": 4}, {"A": 4}, {"A": 4}, {"A": 4}, {"A": 4}, {"A": 4}, {"A": 4}, {"A": 4}, {"A": 4}, {"A": 4}, {"A": 4}, {"A": 4}, {"A": 4}, {"A": 4}, {"A": 4}, {"A": 4}, {"A": 4}, {"A": 4}, {"A": 4}, {"A": 4}, {"A": 4}, {"A": 4}, {"A": 4}, {"A": 4}, {"A": 4}, {"A": 4}, {"A": 1}]}, {"11": [{"A": 2}, {"A": 2}, {"A": 2}, {"A": 2}, {"A": 2}, {"A": 2}, {"A": 2}, {"A": 4}, {"A": 2}, {"A": 2}, {"A": 2}, {"A": 4}, {"A": 2}, {"A": 2}, {"A": 2}, {"A": 2}, {"A": 4}, {"A": 2}, {"A": 2}, {"A": 4}, {"A": 2}, {"A": 4}, {"A": 2}, {"A": 2}, {"A": 2}, {"A": 2}, {"A": 2}, {"A": 4}, {"A": 2}, {"A": 2}, {"A": 2}, {"A": 2}, {"A": 2}, {"A": 2}, {"A": 2}, {"A": 5}, {"A": 5}, {"A": 2}, {"A": 2}, {"A": 2}, {"A": 2}, {"A": 2}, {"A": 2}, {"A": 2}, {"A": 2}, {"A": 2}, {"A": 2}, {"A": 2}, {"A": 2}, {"A": 2}]}, {"12": [{"A": 4}, {"A": 4}, {"A": 4}, {"A": 4}, {"A": 4}, {"A": 4}, {"A": 4}, {"A": 4}, {"A": 4}, {"A": 4}, {"A": 4}, {"A": 4}, {"A": 4}, {"A": 4}, {"A": 4}, {"A": 4}, {"A": 4}, {"A": 4}, {"A": 4}, {"A": 4}, {"A": 4}, {"A": 4}, {"A": 4}, {"A": 1}, {"A": 4}, {"A": 4}, {"A": 4}, {"A": 4}, {"A": 4}, {"A": 4}, {"A": 4}, {"A": 4}, {"A": 4}, {"A": 4}, {"A": 4}, {"A": 4}, {"A": 4}, {"A": 4}, {"A": 4}, {"A": 4}, {"A": 4}, {"A": 4}, {"A": 4}, {"A": 4}, {"A": 4}, {"A": 4}, {"A": 4}, {"A": 4}, {"A": 1}, {"A": 4}]}, {"13": [{"A": 4}, {"A": 4}, {"A": 4}, {"A": 4}, {"A": 4}, {"A": 4}, {"A": 4}, {"A": 4}, {"A": 4}, {"A": 4}, {"A": 4}, {"A": 4}, {"A": 4}, {"A": 4}, {"A": 4}, {"A": 4}, {"A": 4}, {"A": 4}, {"A": 4}, {"A": 4}, {"A": 4}, {"A": 4}, {"A": 4}, {"A": 4}, {"A": 4}, {"A": 4}, {"A": 4}, {"A": 4}, {"A": 4}, {"A": 4}, {"A": 4}, {"A": 4}, {"A": 4}, {"A": 4}, {"A": 4}, {"A": 4}, {"A": 4}, {"A": 4}, {"A": 4}, {"A": 4}, {"A": 4}, {"A": 4}, {"A": 4}, {"A": 4}, {"A": 4}, {"A": 4}, {"A": 4}, {"A": 4}, {"A": 4}, {"A": 4}]}, {"14": [{"A": 4}, {"A": 4}, {"A": 4}, {"A": 4}, {"A": 4}, {"A": 4}, {"A": 4}, {"A": 4}, {"A": 4}, {"A": 4}, {"A": 4}, {"A": 4}, {"A": 4}, {"A": 4}, {"A": 4}, {"A": 4}, {"A": 4}, {"A": 4}, {"A": 4}, {"A": 4}, {"A": 4}, {"A": 4}, {"A": 4}, {"A": 4}, {"A": 4}, {"A": 4}, {"A": 4}, {"A": 4}, {"A": 4}, {"A": 4}, {"A": 4}, {"A": 4}, {"A": 4}, {"A": 4}, {"A": 4}, {"A": 4}, {"A": 4}, {"A": 4}, {"A": 4}, {"A": 4}, {"A": 4}, {"A": 4}, {"A": 4}, {"A": 4}, {"A": 4}, {"A": 4}, {"A": 4}, {"A": 4}, {"A": 4}, {"A": 4}]}, {"15": [{"A": 5}, {"A": 5}, {"A": 5}, {"A": 5}, {"A": 5}, {"A": 5}, {"A": 5}, {"A": 5}, {"A": 5}, {"A": 5}, {"A": 5}, {"A": 5}, {"A": 5}, {"A": 5}, {"A": 5}, {"A": 5}, {"A": 5}, {"A": 5}, {"A": 5}, {"A": 5}, {"A": 5}, {"A": 5}, {"A": 5}, {"A": 5}, {"A": 5}, {"A": 5}, {"A": 5}, {"A": 5}, {"A": 5}, {"A": 5}, {"A": 5}, {"A": 5}, {"A": 5}, {"A": 5}, {"A": 5}, {"A": 5}, {"A": 5}, {"A": 5}, {"A": 5}, {"A": 5}, {"A": 5}, {"A": 5}, {"A": 5}, {"A": 5}, {"A": 5}, {"A": 5}, {"A": 5}, {"A": 5}, {"A": 5}, {"A": 5}]}, {"16": [{"A": 4}, {"A": 4}, {"A": 4}, {"A": 4}, {"A": 4}, {"A": 4}, {"A": 4}, {"A": 4}, {"A": 4}, {"A": 4}, {"A": 4}, {"A": 4}, {"A": 4}, {"A": 4}, {"A": 4}, {"A": 4}, {"A": 4}, {"A": 4}, {"A": 4}, {"A": 4}, {"A": 4}, {"A": 4}, {"A": 4}, {"A": 4}, {"A": 4}, {"A": 4}, {"A": 4}, {"A": 4}, {"A": 4}, {"A": 4}, {"A": 4}, {"A": 4}, {"A": 4}, {"A": 4}, {"A": 4}, {"A": 4}, {"A": 4}, {"A": 4}, {"A": 4}, {"A": 4}, {"A": 4}, {"A": 4}, {"A": 4}, {"A": 4}, {"A": 4}, {"A": 4}, {"A": 4}, {"A": 4}, {"A": 4}, {"A": 4}]}, {"17": [{"A": 4}, {"A": 4}, {"A": 4}, {"A": 4}, {"A": 4}, {"A": 4}, {"A": 4}, {"A": 4}, {"A": 4}, {"A": 4}, {"A": 4}, {"A": 4}, {"A": 4}, {"A": 4}, {"A": 4}, {"A": 4}, {"A": 4}, {"A": 4}, {"A": 4}, {"A": 4}, {"A": 4}, {"A": 4}, {"A": 4}, {"A": 4}, {"A": 4}, {"A": 4}, {"A": 4}, {"A": 4}, {"A": 4}, {"A": 4}, {"A": 4}, {"A": 4}, {"A": 4}, {"A": 4}, {"A": 4}, {"A": 4}, {"A": 4}, {"A": 4}, {"A": 4}, {"A": 4}, {"A": 4}, {"A": 4}, {"A": 4}, {"A": 4}, {"A": 4}, {"A": 4}, {"A": 4}, {"A": 4}, {"A": 4}, {"A": 4}]}, {"18": [{"A": 3}, {"A": 3}, {"A": 3}, {"A": 3}, {"A": 3}, {"A": 3}, {"A": 3}, {"A": 3}, {"A": 3}, {"A": 3}, {"A": 3}, {"A": 3}, {"A": 3}, {"A": 3}, {"A": 3}, {"A": 3}, {"A": 3}, {"A": 3}, {"A": 3}, {"A": 3}, {"A": 3}, {"A": 3}, {"A": 3}, {"A": 3}, {"A": 3}, {"A": 3}, {"A": 3}, {"A": 3}, {"A": 3}, {"A": 3}, {"A": 3}, {"A": 3}, {"A": 3}, {"A": 3}, {"A": 3}, {"A": 3}, {"A": 3}, {"A": 3}, {"A": 3}, {"A": 3}, {"A": 3}, {"A": 3}, {"A": 3}, {"A": 3}, {"A": 3}, {"A": 3}, {"A": 3}, {"A": 3}, {"A": 3}, {"A": 3}]}, {"19": [{"A": 4}, {"A": 4}, {"A": 4}, {"A": 4}, {"A": 2}, {"A": 4}, {"A": 2}, {"A": 2}, {"A": 4}, {"A": 4}, {"A": 2}, {"A": 4}, {"A": 2}, {"A": 4}, {"A": 4}, {"A": 2}, {"A": 2}, {"A": 2}, {"A": 2}, {"A": 2}, {"A": 4}, {"A": 2}, {"A": 2}, {"A": 4}, {"A": 4}, {"A": 4}, {"A": 2}, {"A": 4}, {"A": 4}, {"A": 2}, {"A": 2}, {"A": 4}, {"A": 4}, {"A": 2}, {"A": 4}, {"A": 2}, {"A": 2}, {"A": 4}, {"A": 4}, {"A": 4}, {"A": 4}, {"A": 4}, {"A": 4}, {"A": 4}, {"A": 4}, {"A": 4}, {"A": 2}, {"A": 4}, {"A": 4}, {"A": 4}]}, {"20": [{"A": 4}, {"A": 4}, {"A": 4}, {"A": 4}, {"A": 4}, {"A": 1}, {"A": 4}, {"A": 1}, {"A": 4}, {"A": 1}, {"A": 1}, {"A": 1}, {"A": 1}, {"A": 4}, {"A": 4}, {"A": 4}, {"A": 1}, {"A": 1}, {"A": 1}, {"A": 4}, {"A": 4}, {"A": 1}, {"A": 4}, {"A": 1}, {"A": 4}, {"A": 4}, {"A": 1}, {"A": 1}, {"A": 4}, {"A": 1}, {"A": 1}, {"A": 1}, {"A": 1}, {"A": 4}, {"A": 1}, {"A": 1}, {"A": 1}, {"A": 4}, {"A": 1}, {"A": 1}, {"A": 4}, {"A": 1}, {"A": 4}, {"A": 1}, {"A": 4}, {"A": 4}, {"A": 1}, {"A": 4}, {"A": 4}, {"A": 1}]}, {"21": [{"A": 2}, {"A": 2}, {"A": 2}, {"A": 2}, {"A": 2}, {"A": 2}, {"A": 2}, {"A": 2}, {"A": 2}, {"A": 2}, {"A": 2}, {"A": 2}, {"A": 2}, {"A": 2}, {"A": 2}, {"A": 2}, {"A": 2}, {"A": 4}, {"A": 2}, {"A": 2}, {"A": 2}, {"A": 3}, {"A": 2}, {"A": 2}, {"A": 2}, {"A": 2}, {"A": 2}, {"A": 2}, {"A": 2}, {"A": 2}, {"A": 2}, {"A": 2}, {"A": 2}, {"A": 2}, {"A": 2}, {"A": 2}, {"A": 2}, {"A": 2}, {"A": 2}, {"A": 2}, {"A": 2}, {"A": 2}, {"A": 3}, {"A": 2}, {"A": 2}, {"A": 2}, {"A": 2}, {"A": 2}, {"A": 2}, {"A": 2}]}, {"22": [{"A": 4}, {"A": 4}, {"A": 4}, {"A": 4}, {"A": 4}, {"A": 4}, {"A": 4}, {"A": 4}, {"A": 4}, {"A": 4}, {"A": 4}, {"A": 4}, {"A": 4}, {"A": 4}, {"A": 4}, {"A": 4}, {"A": 1}, {"A": 4}, {"A": 4}, {"A": 4}, {"A": 4}, {"A": 4}, {"A": 4}, {"A": 4}, {"A": 4}, {"A": 4}, {"A": 4}, {"A": 4}, {"A": 4}, {"A": 4}, {"A": 4}, {"A": 4}, {"A": 4}, {"A": 4}, {"A": 4}, {"A": 4}, {"A": 4}, {"A": 4}, {"A": 4}, {"A": 4}, {"A": 4}, {"A": 4}, {"A": 4}, {"A": 4}, {"A": 4}, {"A": 4}, {"A": 4}, {"A": 4}, {"A": 4}, {"A": 4}]}, {"23": [{"A": 4}, {"A": 1}, {"A": 4}, {"A": 4}, {"A": 4}, {"A": 4}, {"A": 4}, {"A": 4}, {"A": 4}, {"A": 4}, {"A": 4}, {"A": 4}, {"A": 1}, {"A": 1}, {"A": 4}, {"A": 1}, {"A": 1}, {"A": 4}, {"A": 1}, {"A": 4}, {"A": 1}, {"A": 4}, {"A": 4}, {"A": 4}, {"A": 4}, {"A": 4}, {"A": 4}, {"A": 4}, {"A": 4}, {"A": 1}, {"A": 1}, {"A": 4}, {"A": 4}, {"A": 1}, {"A": 1}, {"A": 1}, {"A": 1}, {"A": 1}, {"A": 4}, {"A": 1}, {"A": 4}, {"A": 1}, {"A": 4}, {"A": 4}, {"A": 1}, {"A": 5}, {"A": 4}, {"A": 1}, {"A": 4}, {"A": 1}]}, {"24": [{"A": 4}, {"A": 4}, {"A": 4}, {"A": 4}, {"A": 1}, {"A": 4}, {"A": 4}, {"A": 1}, {"A": 4}, {"A": 4}, {"A": 4}, {"A": 4}, {"A": 4}, {"A": 4}, {"A": 4}, {"A": 1}, {"A": 4}, {"A": 4}, {"A": 1}, {"A": 4}, {"A": 1}, {"A": 4}, {"A": 4}, {"A": 4}, {"A": 1}, {"A": 1}, {"A": 1}, {"A": 4}, {"A": 1}, {"A": 1}, {"A": 4}, {"A": 4}, {"A": 4}, {"A": 4}, {"A": 4}, {"A": 1}, {"A": 4}, {"A": 4}, {"A": 4}, {"A": 4}, {"A": 4}, {"A": 4}, {"A": 4}, {"A": 1}, {"A": 1}, {"A": 1}, {"A": 4}, {"A": 4}, {"A": 4}, {"A": 4}]}, {"25": [{"A": 2}, {"A": 2}, {"A": 2}, {"A": 4}, {"A": 2}, {"A": 4}, {"A": 4}, {"A": 2}, {"A": 2}, {"A": 4}, {"A": 4}, {"A": 4}, {"A": 4}, {"A": 2}, {"A": 4}, {"A": 4}, {"A": 2}, {"A": 2}, {"A": 2}, {"A": 4}, {"A": 2}, {"A": 2}, {"A": 2}, {"A": 2}, {"A": 2}, {"A": 2}, {"A": 4}, {"A": 2}, {"A": 2}, {"A": 2}, {"A": 4}, {"A": 2}, {"A": 4}, {"A": 4}, {"A": 2}, {"A": 2}, {"A": 4}, {"A": 4}, {"A": 4}, {"A": 2}, {"A": 2}, {"A": 2}, {"A": 2}, {"A": 4}, {"A": 4}, {"A": 2}, {"A": 4}, {"A": 4}, {"A": 2}, {"A": 4}]}, {"26": [{"A": 4}, {"A": 4}, {"A": 4}, {"A": 4}, {"A": 4}, {"A": 4}, {"A": 4}, {"A": 4}, {"A": 4}, {"A": 4}, {"A": 4}, {"A": 4}, {"A": 4}, {"A": 4}, {"A": 4}, {"A": 4}, {"A": 4}, {"A": 4}, {"A": 4}, {"A": 4}, {"A": 4}, {"A": 4}, {"A": 4}, {"A": 4}, {"A": 4}, {"A": 4}, {"A": 4}, {"A": 4}, {"A": 4}, {"A": 4}, {"A": 4}, {"A": 4}, {"A": 4}, {"A": 4}, {"A": 4}, {"A": 4}, {"A": 4}, {"A": 4}, {"A": 4}, {"A": 4}, {"A": 4}, {"A": 4}, {"A": 4}, {"A": 4}, {"A": 4}, {"A": 4}, {"A": 4}, {"A": 4}, {"A": 4}, {"A": 4}]}, {"27": [{"A": 5}, {"A": 5}, {"A": 5}, {"A": 5}, {"A": 5}, {"A": 5}, {"A": 5}, {"A": 5}, {"A": 5}, {"A": 5}, {"A": 5}, {"A": 5}, {"A": 5}, {"A": 5}, {"A": 5}, {"A": 5}, {"A": 5}, {"A": 5}, {"A": 5}, {"A": 5}, {"A": 5}, {"A": 5}, {"A": 5}, {"A": 5}, {"A": 5}, {"A": 5}, {"A": 5}, {"A": 5}, {"A": 5}, {"A": 5}, {"A": 5}, {"A": 5}, {"A": 5}, {"A": 5}, {"A": 5}, {"A": 5}, {"A": 5}, {"A": 5}, {"A": 5}, {"A": 5}, {"A": 5}, {"A": 4}, {"A": 5}, {"A": 5}, {"A": 5}, {"A": 5}, {"A": 5}, {"A": 5}, {"A": 5}, {"A": 5}]}, {"28": [{"A": 3}, {"A": 5}, {"A": 5}, {"A": 5}, {"A": 3}, {"A": 5}, {"A": 3}, {"A": 3}, {"A": 3}, {"A": 5}, {"A": 5}, {"A": 3}, {"A": 5}, {"A": 5}, {"A": 5}, {"A": 5}, {"A": 5}, {"A": 3}, {"A": 3}, {"A": 5}, {"A": 5}, {"A": 5}, {"A": 3}, {"A": 5}, {"A": 5}, {"A": 3}, {"A": 5}, {"A": 5}, {"A": 5}, {"A": 5}, {"A": 5}, {"A": 5}, {"A": 5}, {"A": 3}, {"A": 5}, {"A": 3}, {"A": 3}, {"A": 5}, {"A": 5}, {"A": 5}, {"A": 5}, {"A": 5}, {"A": 5}, {"A": 5}, {"A": 5}, {"A": 5}, {"A": 5}, {"A": 5}, {"A": 5}, {"A": 5}]}, {"29": [{"A": 4}, {"A": 4}, {"A": 4}, {"A": 4}, {"A": 4}, {"A": 4}, {"A": 4}, {"A": 4}, {"A": 4}, {"A": 4}, {"A": 4}, {"A": 4}, {"A": 4}, {"A": 4}, {"A": 4}, {"A": 4}, {"A": 4}, {"A": 4}, {"A": 4}, {"A": 4}, {"A": 4}, {"A": 4}, {"A": 4}, {"A": 4}, {"A": 4}, {"A": 4}, {"A": 4}, {"A": 4}, {"A": 4}, {"A": 4}, {"A": 4}, {"A": 4}, {"A": 4}, {"A": 4}, {"A": 4}, {"A": 4}, {"A": 4}, {"A": 4}, {"A": 4}, {"A": 4}, {"A": 4}, {"A": 4}, {"A": 4}, {"A": 4}, {"A": 4}, {"A": 4}, {"A": 4}, {"A": 4}, {"A": 4}, {"A": 4}]}, {"30": [{"A": 5}, {"A": 5}, {"A": 3}, {"A": 3}, {"A": 3}, {"A": 3}, {"A": 3}, {"A": 3}, {"A": 5}, {"A": 5}, {"A": 5}, {"A": 3}, {"A": 5}, {"A": 5}, {"A": 3}, {"A": 5}, {"A": 3}, {"A": 3}, {"A": 5}, {"A": 3}, {"A": 3}, {"A": 5}, {"A": 5}, {"A": 3}, {"A": 3}, {"A": 5}, {"A": 3}, {"A": 5}, {"A": 3}, {"A": 3}, {"A": 3}, {"A": 3}, {"A": 3}, {"A": 5}, {"A": 5}, {"A": 5}, {"A": 5}, {"A": 3}, {"A": 5}, {"A": 3}, {"A": 3}, {"A": 3}, {"A": 5}, {"A": 5}, {"A": 5}, {"A": 3}, {"A": 5}, {"A": 5}, {"A": 3}, {"A": 5}]}, {"31": [{"A": 2}, {"A": 4}, {"A": 4}, {"A": 4}, {"A": 4}, {"A": 2}, {"A": 4}, {"A": 4}, {"A": 2}, {"A": 2}, {"A": 4}, {"A": 4}, {"A": 2}, {"A": 4}, {"A": 4}, {"A": 2}, {"A": 4}, {"A": 4}, {"A": 4}, {"A": 4}, {"A": 4}, {"A": 4}, {"A": 4}, {"A": 2}, {"A": 4}, {"A": 4}, {"A": 4}, {"A": 4}, {"A": 2}, {"A": 4}, {"A": 4}, {"A": 4}, {"A": 4}, {"A": 4}, {"A": 4}, {"A": 2}, {"A": 4}, {"A": 4}, {"A": 4}, {"A": 2}, {"A": 2}, {"A": 2}, {"A": 2}, {"A": 2}, {"A": 4}, {"A": 4}, {"A": 4}, {"A": 2}, {"A": 4}, {"A": 4}]}, {"32": [{"A": 4}, {"A": 4}, {"A": 2}, {"A": 2}, {"A": 4}, {"A": 4}, {"A": 2}, {"A": 4}, {"A": 2}, {"A": 2}, {"A": 4}, {"A": 4}, {"A": 2}, {"A": 4}, {"A": 4}, {"A": 2}, {"A": 2}, {"A": 4}, {"A": 4}, {"A": 4}, {"A": 2}, {"A": 4}, {"A": 4}, {"A": 4}, {"A": 4}, {"A": 4}, {"A": 4}, {"A": 4}, {"A": 4}, {"A": 4}, {"A": 2}, {"A": 4}, {"A": 4}, {"A": 4}, {"A": 4}, {"A": 4}, {"A": 2}, {"A": 4}, {"A": 2}, {"A": 4}, {"A": 4}, {"A": 4}, {"A": 4}, {"A": 4}, {"A": 2}, {"A": 4}, {"A": 2}, {"A": 2}, {"A": 2}, {"A": 4}]}, {"33": [{"A": 4}, {"A": 4}, {"A": 4}, {"A": 4}, {"A": 2}, {"A": 4}, {"A": 4}, {"A": 4}, {"A": 4}, {"A": 4}, {"A": 2}, {"A": 2}, {"A": 2}, {"A": 4}, {"A": 2}, {"A": 2}, {"A": 2}, {"A": 4}, {"A": 4}, {"A": 4}, {"A": 4}, {"A": 4}, {"A": 4}, {"A": 4}, {"A": 4}, {"A": 4}, {"A": 4}, {"A": 4}, {"A": 4}, {"A": 4}, {"A": 4}, {"A": 4}, {"A": 4}, {"A": 4}, {"A": 2}, {"A": 4}, {"A": 2}, {"A": 4}, {"A": 2}, {"A": 4}, {"A": 4}, {"A": 4}, {"A": 4}, {"A": 4}, {"A": 2}, {"A": 4}, {"A": 2}, {"A": 4}, {"A": 4}, {"A": 4}]}, {"34": [{"A": 3}, {"A": 3}, {"A": 3}, {"A": 3}, {"A": 3}, {"A": 3}, {"A": 3}, {"A": 3}, {"A": 3}, {"A": 3}, {"A": 3}, {"A": 3}, {"A": 3}, {"A": 3}, {"A": 3}, {"A": 3}, {"A": 3}, {"A": 3}, {"A": 3}, {"A": 3}, {"A": 3}, {"A": 3}, {"A": 3}, {"A": 3}, {"A": 3}, {"A": 3}, {"A": 3}, {"A": 3}, {"A": 3}, {"A": 3}, {"A": 3}, {"A": 3}, {"A": 3}, {"A": 3}, {"A": 3}, {"A": 3}, {"A": 3}, {"A": 3}, {"A": 3}, {"A": 4}, {"A": 3}, {"A": 3}, {"A": 3}, {"A": 3}, {"A": 3}, {"A": 3}, {"A": 3}, {"A": 3}, {"A": 3}, {"A": 3}]}, {"35": [{"A": 3}, {"A": 3}, {"A": 3}, {"A": 3}, {"A": 3}, {"A": 3}, {"A": 3}, {"A": 3}, {"A": 3}, {"A": 3}, {"A": 3}, {"A": 3}, {"A": 3}, {"A": 3}, {"A": 3}, {"A": 3}, {"A": 3}, {"A": 3}, {"A": 3}, {"A": 3}, {"A": 3}, {"A": 3}, {"A": 3}, {"A": 3}, {"A": 3}, {"A": 3}, {"A": 3}, {"A": 3}, {"A": 3}, {"A": 3}, {"A": 3}, {"A": 3}, {"A": 3}, {"A": 3}, {"A": 3}, {"A": 3}, {"A": 3}, {"A": 3}, {"A": 3}, {"A": 3}, {"A": 3}, {"A": 3}, {"A": 3}, {"A": 3}, {"A": 3}, {"A": 3}, {"A": 3}, {"A": 3}, {"A": 3}, {"A": 3}]}, {"36": [{"A": 4}, {"A": 4}, {"A": 4}, {"A": 4}, {"A": 4}, {"A": 4}, {"A": 4}, {"A": 4}, {"A": 2}, {"A": 4}, {"A": 4}, {"A": 4}, {"A": 4}, {"A": 2}, {"A": 4}, {"A": 4}, {"A": 2}, {"A": 4}, {"A": 4}, {"A": 4}, {"A": 4}, {"A": 4}, {"A": 2}, {"A": 4}, {"A": 4}, {"A": 4}, {"A": 2}, {"A": 4}, {"A": 4}, {"A": 4}, {"A": 4}, {"A": 4}, {"A": 4}, {"A": 4}, {"A": 4}, {"A": 4}, {"A": 2}, {"A": 4}, {"A": 4}, {"A": 4}, {"A": 4}, {"A": 4}, {"A": 4}, {"A": 4}, {"A": 4}, {"A": 4}, {"A": 2}, {"A": 4}, {"A": 4}, {"A": 4}]}, {"37": [{"A": 1}, {"A": 1}, {"A": 1}, {"A": 1}, {"A": 1}, {"A": 1}, {"A": 1}, {"A": 4}, {"A": 1}, {"A": 4}, {"A": 1}, {"A": 4}, {"A": 4}, {"A": 1}, {"A": 1}, {"A": 1}, {"A": 4}, {"A": 1}, {"A": 1}, {"A": 4}, {"A": 4}, {"A": 1}, {"A": 4}, {"A": 1}, {"A": 4}, {"A": 1}, {"A": 1}, {"A": 1}, {"A": 4}, {"A": 4}, {"A": 4}, {"A": 4}, {"A": 4}, {"A": 1}, {"A": 1}, {"A": 1}, {"A": 4}, {"A": 1}, {"A": 1}, {"A": 4}, {"A": 1}, {"A": 1}, {"A": 4}, {"A": 1}, {"A": 1}, {"A": 4}, {"A": 1}, {"A": 4}, {"A": 1}, {"A": 1}]}, {"38": [{"A": 4}, {"A": 4}, {"A": 4}, {"A": 4}, {"A": 4}, {"A": 1}, {"A": 1}, {"A": 4}, {"A": 4}, {"A": 4}, {"A": 1}, {"A": 4}, {"A": 4}, {"A": 1}, {"A": 1}, {"A": 1}, {"A": 1}, {"A": 4}, {"A": 4}, {"A": 4}, {"A": 4}, {"A": 4}, {"A": 4}, {"A": 4}, {"A": 4}, {"A": 1}, {"A": 4}, {"A": 1}, {"A": 4}, {"A": 4}, {"A": 4}, {"A": 4}, {"A": 1}, {"A": 1}, {"A": 1}, {"A": 1}, {"A": 1}, {"A": 4}, {"A": 1}, {"A": 4}, {"A": 4}, {"A": 4}, {"A": 1}, {"A": 4}, {"A": 4}, {"A": 4}, {"A": 3}, {"A": 4}, {"A": 1}, {"A": 1}]}, {"39": [{"A": 3}, {"A": 3}, {"A": 3}, {"A": 3}, {"A": 3}, {"A": 3}, {"A": 3}, {"A": 3}, {"A": 3}, {"A": 3}, {"A": 3}, {"A": 3}, {"A": 3}, {"A": 3}, {"A": 3}, {"A": 3}, {"A": 3}, {"A": 3}, {"A": 3}, {"A": 3}, {"A": 3}, {"A": 3}, {"A": 3}, {"A": 3}, {"A": 3}, {"A": 3}, {"A": 3}, {"A": 3}, {"A": 3}, {"A": 3}, {"A": 3}, {"A": 3}, {"A": 3}, {"A": 3}, {"A": 3}, {"A": 3}, {"A": 3}, {"A": 3}, {"A": 3}, {"A": 3}, {"A": 3}, {"A": 3}, {"A": 3}, {"A": 3}, {"A": 3}, {"A": 3}, {"A": 3}, {"A": 3}, {"A": 3}, {"A": 3}]}, {"40": [{"A": 2}, {"A": 2}, {"A": 4}, {"A": 4}, {"A": 4}, {"A": 4}, {"A": 2}, {"A": 2}, {"A": 2}, {"A": 2}, {"A": 2}, {"A": 4}, {"A": 4}, {"A": 2}, {"A": 2}, {"A": 2}, {"A": 2}, {"A": 2}, {"A": 4}, {"A": 2}, {"A": 2}, {"A": 4}, {"A": 2}, {"A": 2}, {"A": 4}, {"A": 2}, {"A": 2}, {"A": 2}, {"A": 4}, {"A": 2}, {"A": 4}, {"A": 4}, {"A": 2}, {"A": 2}, {"A": 4}, {"A": 4}, {"A": 2}, {"A": 2}, {"A": 2}, {"A": 2}, {"A": 2}, {"A": 2}, {"A": 2}, {"A": 2}, {"A": 2}, {"A": 2}, {"A": 4}, {"A": 2}, {"A": 2}, {"A": 2}]}, {"41": [{"A": 5}, {"A": 5}, {"A": 5}, {"A": 5}, {"A": 5}, {"A": 5}, {"A": 5}, {"A": 5}, {"A": 5}, {"A": 5}, {"A": 5}, {"A": 5}, {"A": 5}, {"A": 5}, {"A": 5}, {"A": 5}, {"A": 5}, {"A": 2}, {"A": 5}, {"A": 5}, {"A": 5}, {"A": 5}, {"A": 5}, {"A": 2}, {"A": 5}, {"A": 5}, {"A": 5}, {"A": 5}, {"A": 5}, {"A": 5}, {"A": 5}, {"A": 5}, {"A": 2}, {"A": 5}, {"A": 5}, {"A": 2}, {"A": 5}, {"A": 5}, {"A": 5}, {"A": 5}, {"A": 5}, {"A": 5}, {"A": 5}, {"A": 5}, {"A": 5}, {"A": 5}, {"A": 5}, {"A": 5}, {"A": 5}, {"A": 5}]}, {"42": [{"A": 3}, {"A": 3}, {"A": 3}, {"A": 3}, {"A": 2}, {"A": 3}, {"A": 3}, {"A": 3}, {"A": 3}, {"A": 3}, {"A": 3}, {"A": 3}, {"A": 3}, {"A": 3}, {"A": 3}, {"A": 3}, {"A": 3}, {"A": 3}, {"A": 3}, {"A": 3}, {"A": 3}, {"A": 3}, {"A": 3}, {"A": 3}, {"A": 3}, {"A": 3}, {"A": 4}, {"A": 3}, {"A": 3}, {"A": 3}, {"A": 3}, {"A": 3}, {"A": 3}, {"A": 3}, {"A": 3}, {"A": 3}, {"A": 3}, {"A": 3}, {"A": 3}, {"A": 3}, {"A": 3}, {"A": 3}, {"A": 3}, {"A": 3}, {"A": 3}, {"A": 3}, {"A": 3}, {"A": 3}, {"A": 3}, {"A": 3}]}, {"43": [{"A": 4}, {"A": 2}, {"A": 4}, {"A": 4}, {"A": 4}, {"A": 4}, {"A": 4}, {"A": 4}, {"A": 4}, {"A": 4}, {"A": 4}, {"A": 4}, {"A": 4}, {"A": 4}, {"A": 4}, {"A": 4}, {"A": 4}, {"A": 2}, {"A": 4}, {"A": 4}, {"A": 4}, {"A": 4}, {"A": 2}, {"A": 4}, {"A": 4}, {"A": 4}, {"A": 4}, {"A": 4}, {"A": 4}, {"A": 4}, {"A": 4}, {"A": 4}, {"A": 4}, {"A": 4}, {"A": 4}, {"A": 4}, {"A": 4}, {"A": 4}, {"A": 4}, {"A": 4}, {"A": 4}, {"A": 4}, {"A": 4}, {"A": 4}, {"A": 4}, {"A": 4}, {"A": 4}, {"A": 4}, {"A": 4}, {"A": 4}]}, {"44": [{"A": 5}, {"A": 5}, {"A": 5}, {"A": 5}, {"A": 5}, {"A": 5}, {"A": 5}, {"A": 5}, {"A": 5}, {"A": 5}, {"A": 5}, {"A": 5}, {"A": 5}, {"A": 5}, {"A": 5}, {"A": 5}, {"A": 5}, {"A": 5}, {"A": 5}, {"A": 5}, {"A": 5}, {"A": 5}, {"A": 5}, {"A": 5}, {"A": 5}, {"A": 5}, {"A": 5}, {"A": 5}, {"A": 5}, {"A": 5}, {"A": 5}, {"A": 5}, {"A": 5}, {"A": 5}, {"A": 5}, {"A": 5}, {"A": 5}, {"A": 5}, {"A": 5}, {"A": 5}, {"A": 5}, {"A": 5}, {"A": 5}, {"A": 5}, {"A": 5}, {"A": 5}, {"A": 5}, {"A": 5}, {"A": 5}, {"A": 5}]}, {"45": [{"A": 4}, {"A": 4}, {"A": 4}, {"A": 4}, {"A": 4}, {"A": 4}, {"A": 4}, {"A": 4}, {"A": 4}, {"A": 4}, {"A": 4}, {"A": 4}, {"A": 4}, {"A": 4}, {"A": 4}, {"A": 4}, {"A": 4}, {"A": 4}, {"A": 4}, {"A": 4}, {"A": 4}, {"A": 4}, {"A": 4}, {"A": 4}, {"A": 4}, {"A": 4}, {"A": 4}, {"A": 4}, {"A": 4}, {"A": 4}, {"A": 4}, {"A": 4}, {"A": 4}, {"A": 4}, {"A": 4}, {"A": 4}, {"A": 4}, {"A": 4}, {"A": 4}, {"A": 4}, {"A": 4}, {"A": 4}, {"A": 4}, {"A": 4}, {"A": 4}, {"A": 4}, {"A": 4}, {"A": 4}, {"A": 4}, {"A": 4}]}, {"46": [{"A": 3}, {"A": 3}, {"A": 3}, {"A": 3}, {"A": 3}, {"A": 3}, {"A": 3}, {"A": 3}, {"A": 3}, {"A": 3}, {"A": 3}, {"A": 3}, {"A": 3}, {"A": 3}, {"A": 3}, {"A": 3}, {"A": 3}, {"A": 3}, {"A": 3}, {"A": 3}, {"A": 3}, {"A": 3}, {"A": 3}, {"A": 3}, {"A": 3}, {"A": 3}, {"A": 3}, {"A": 3}, {"A": 3}, {"A": 3}, {"A": 3}, {"A": 3}, {"A": 3}, {"A": 3}, {"A": 3}, {"A": 3}, {"A": 3}, {"A": 3}, {"A": 3}, {"A": 3}, {"A": 3}, {"A": 3}, {"A": 3}, {"A": 3}, {"A": 3}, {"A": 3}, {"A": 3}, {"A": 3}, {"A": 3}, {"A": 3}]}, {"47": [{"A": 4}, {"A": 4}, {"A": 4}, {"A": 4}, {"A": 4}, {"A": 4}, {"A": 4}, {"A": 4}, {"A": 4}, {"A": 4}, {"A": 4}, {"A": 4}, {"A": 4}, {"A": 4}, {"A": 4}, {"A": 4}, {"A": 4}, {"A": 4}, {"A": 4}, {"A": 4}, {"A": 4}, {"A": 4}, {"A": 4}, {"A": 4}, {"A": 4}, {"A": 4}, {"A": 4}, {"A": 4}, {"A": 4}, {"A": 4}, {"A": 4}, {"A": 4}, {"A": 4}, {"A": 4}, {"A": 4}, {"A": 4}, {"A": 4}, {"A": 4}, {"A": 4}, {"A": 4}, {"A": 4}, {"A": 4}, {"A": 4}, {"A": 4}, {"A": 4}, {"A": 4}, {"A": 4}, {"A": 4}, {"A": 4}, {"A": 4}]}, {"48": [{"A": 5}, {"A": 5}, {"A": 5}, {"A": 5}, {"A": 5}, {"A": 5}, {"A": 5}, {"A": 5}, {"A": 5}, {"A": 5}, {"A": 5}, {"A": 5}, {"A": 5}, {"A": 5}, {"A": 5}, {"A": 5}, {"A": 5}, {"A": 5}, {"A": 5}, {"A": 5}, {"A": 5}, {"A": 5}, {"A": 5}, {"A": 5}, {"A": 5}, {"A": 4}, {"A": 5}, {"A": 5}, {"A": 5}, {"A": 5}, {"A": 5}, {"A": 5}, {"A": 5}, {"A": 5}, {"A": 5}, {"A": 5}, {"A": 5}, {"A": 5}, {"A": 5}, {"A": 5}, {"A": 5}, {"A": 5}, {"A": 5}, {"A": 5}, {"A": 5}, {"A": 5}, {"A": 5}, {"A": 5}, {"A": 5}, {"A": 5}]}, {"49": [{"A": 5}, {"A": 5}, {"A": 5}, {"A": 5}, {"A": 5}, {"A": 5}, {"A": 5}, {"A": 5}, {"A": 5}, {"A": 5}, {"A": 5}, {"A": 5}, {"A": 5}, {"A": 5}, {"A": 5}, {"A": 4}, {"A": 5}, {"A": 5}, {"A": 5}, {"A": 5}, {"A": 5}, {"A": 5}, {"A": 5}, {"A": 5}, {"A": 5}, {"A": 5}, {"A": 5}, {"A": 5}, {"A": 5}, {"A": 5}, {"A": 5}, {"A": 5}, {"A": 5}, {"A": 5}, {"A": 5}, {"A": 5}, {"A": 5}, {"A": 5}, {"A": 5}, {"A": 5}, {"A": 5}, {"A": 5}, {"A": 5}, {"A": 5}, {"A": 5}, {"A": 5}, {"A": 5}, {"A": 5}, {"A": 5}, {"A": 5}]}, {"50": [{"A": 5}, {"A": 5}, {"A": 5}, {"A": 5}, {"A": 5}, {"A": 5}, {"A": 5}, {"A": 5}, {"A": 5}, {"A": 5}, {"A": 5}, {"A": 5}, {"A": 5}, {"A": 5}, {"A": 6}, {"A": 5}, {"A": 5}, {"A": 5}, {"A": 6}, {"A": 5}, {"A": 5}, {"A": 5}, {"A": 5}, {"A": 5}, {"A": 5}, {"A": 5}, {"A": 5}, {"A": 5}, {"A": 5}, {"A": 5}, {"A": 5}, {"A": 5}, {"A": 5}, {"A": 5}, {"A": 5}, {"A": 5}, {"A": 5}, {"A": 5}, {"A": 5}, {"A": 5}, {"A": 5}, {"A": 5}, {"A": 5}, {"A": 5}, {"A": 5}, {"A": 5}, {"A": 5}, {"A": 5}, {"A": 5}, {"A": 5}]}, {"51": [{"A": 4}, {"A": 4}, {"A": 4}, {"A": 4}, {"A": 4}, {"A": 4}, {"A": 4}, {"A": 4}, {"A": 4}, {"A": 4}, {"A": 4}, {"A": 4}, {"A": 4}, {"A": 4}, {"A": 4}, {"A": 4}, {"A": 4}, {"A": 4}, {"A": 4}, {"A": 4}, {"A": 4}, {"A": 4}, {"A": 4}, {"A": 4}, {"A": 4}, {"A": 4}, {"A": 4}, {"A": 4}, {"A": 4}, {"A": 4}, {"A": 4}, {"A": 4}, {"A": 4}, {"A": 4}, {"A": 4}, {"A": 4}, {"A": 4}, {"A": 4}, {"A": 4}, {"A": 4}, {"A": 4}, {"A": 4}, {"A": 4}, {"A": 4}, {"A": 4}, {"A": 4}, {"A": 4}, {"A": 4}, {"A": 4}, {"A": 4}]}, {"52": [{"A": 4}, {"A": 4}, {"A": 4}, {"A": 4}, {"A": 4}, {"A": 4}, {"A": 4}, {"A": 4}, {"A": 4}, {"A": 4}, {"A": 4}, {"A": 4}, {"A": 4}, {"A": 4}, {"A": 4}, {"A": 4}, {"A": 4}, {"A": 4}, {"A": 4}, {"A": 4}, {"A": 4}, {"A": 4}, {"A": 4}, {"A": 4}, {"A": 4}, {"A": 4}, {"A": 4}, {"A": 4}, {"A": 4}, {"A": 4}, {"A": 4}, {"A": 4}, {"A": 4}, {"A": 4}, {"A": 4}, {"A": 4}, {"A": 4}, {"A": 4}, {"A": 4}, {"A": 4}, {"A": 4}, {"A": 4}, {"A": 4}, {"A": 4}, {"A": 4}, {"A": 4}, {"A": 4}, {"A": 4}, {"A": 4}, {"A": 4}]}, {"53": [{"A": 3}, {"A": 3}, {"A": 5}, {"A": 3}, {"A": 3}, {"A": 3}, {"A": 3}, {"A": 3}, {"A": 3}, {"A": 3}, {"A": 3}, {"A": 3}, {"A": 3}, {"A": 3}, {"A": 3}, {"A": 3}, {"A": 3}, {"A": 3}, {"A": 3}, {"A": 3}, {"A": 3}, {"A": 3}, {"A": 3}, {"A": 3}, {"A": 3}, {"A": 3}, {"A": 3}, {"A": 3}, {"A": 3}, {"A": 3}, {"A": 3}, {"A": 3}, {"A": 4}, {"A": 3}, {"A": 3}, {"A": 3}, {"A": 3}, {"A": 3}, {"A": 3}, {"A": 3}, {"A": 3}, {"A": 5}, {"A": 3}, {"A": 3}, {"A": 3}, {"A": 3}, {"A": 3}, {"A": 3}, {"A": 3}, {"A": 3}]}, {"54": [{"A": 2}, {"A": 2}, {"A": 4}, {"A": 4}, {"A": 4}, {"A": 4}, {"A": 4}, {"A": 4}, {"A": 4}, {"A": 4}, {"A": 2}, {"A": 2}, {"A": 4}, {"A": 4}, {"A": 4}, {"A": 4}, {"A": 4}, {"A": 4}, {"A": 4}, {"A": 4}, {"A": 4}, {"A": 4}, {"A": 4}, {"A": 4}, {"A": 4}, {"A": 4}, {"A": 4}, {"A": 2}, {"A": 4}, {"A": 2}, {"A": 4}, {"A": 2}, {"A": 4}, {"A": 2}, {"A": 2}, {"A": 4}, {"A": 4}, {"A": 4}, {"A": 2}, {"A": 4}, {"A": 2}, {"A": 2}, {"A": 4}, {"A": 4}, {"A": 4}, {"A": 4}, {"A": 4}, {"A": 2}, {"A": 2}, {"A": 2}]}, {"55": [{"A": 1}, {"A": 1}, {"A": 1}, {"A": 4}, {"A": 1}, {"A": 1}, {"A": 1}, {"A": 4}, {"A": 1}, {"A": 1}, {"A": 4}, {"A": 4}, {"A": 4}, {"A": 4}, {"A": 1}, {"A": 1}, {"A": 1}, {"A": 1}, {"A": 1}, {"A": 1}, {"A": 4}, {"A": 4}, {"A": 4}, {"A": 4}, {"A": 1}, {"A": 1}, {"A": 1}, {"A": 1}, {"A": 1}, {"A": 1}, {"A": 1}, {"A": 1}, {"A": 1}, {"A": 1}, {"A": 1}, {"A": 4}, {"A": 4}, {"A": 1}, {"A": 1}, {"A": 4}, {"A": 4}, {"A": 1}, {"A": 1}, {"A": 1}, {"A": 1}, {"A": 4}, {"A": 1}, {"A": 1}, {"A": 1}, {"A": 1}]}, {"56": [{"A": 4}, {"A": 4}, {"A": 4}, {"A": 1}, {"A": 4}, {"A": 4}, {"A": 4}, {"A": 1}, {"A": 4}, {"A": 4}, {"A": 1}, {"A": 4}, {"A": 1}, {"A": 4}, {"A": 4}, {"A": 1}, {"A": 1}, {"A": 4}, {"A": 4}, {"A": 1}, {"A": 1}, {"A": 4}, {"A": 1}, {"A": 4}, {"A": 1}, {"A": 4}, {"A": 4}, {"A": 4}, {"A": 1}, {"A": 4}, {"A": 4}, {"A": 1}, {"A": 4}, {"A": 4}, {"A": 4}, {"A": 4}, {"A": 1}, {"A": 4}, {"A": 4}, {"A": 1}, {"A": 4}, {"A": 4}, {"A": 1}, {"A": 4}, {"A": 4}, {"A": 1}, {"A": 4}, {"A": 4}, {"A": 4}, {"A": 1}]}, {"57": [{"A": 4}, {"A": 4}, {"A": 4}, {"A": 4}, {"A": 4}, {"A": 4}, {"A": 4}, {"A": 4}, {"A": 4}, {"A": 4}, {"A": 4}, {"A": 4}, {"A": 2}, {"A": 4}, {"A": 4}, {"A": 2}, {"A": 4}, {"A": 4}, {"A": 4}, {"A": 4}, {"A": 4}, {"A": 4}, {"A": 4}, {"A": 4}, {"A": 4}, {"A": 4}, {"A": 4}, {"A": 4}, {"A": 4}, {"A": 4}, {"A": 4}, {"A": 4}, {"A": 4}, {"A": 4}, {"A": 4}, {"A": 4}, {"A": 2}, {"A": 2}, {"A": 4}, {"A": 2}, {"A": 4}, {"A": 4}, {"A": 4}, {"A": 4}, {"A": 4}, {"A": 4}, {"A": 4}, {"A": 4}, {"A": 2}, {"A": 4}]}, {"58": [{"A": 4}, {"A": 2}, {"A": 4}, {"A": 2}, {"A": 4}, {"A": 4}, {"A": 4}, {"A": 4}, {"A": 4}, {"A": 4}, {"A": 4}, {"A": 4}, {"A": 4}, {"A": 4}, {"A": 4}, {"A": 4}, {"A": 4}, {"A": 4}, {"A": 4}, {"A": 4}, {"A": 4}, {"A": 4}, {"A": 4}, {"A": 4}, {"A": 4}, {"A": 4}, {"A": 2}, {"A": 2}, {"A": 4}, {"A": 4}, {"A": 4}, {"A": 4}, {"A": 4}, {"A": 4}, {"A": 4}, {"A": 2}, {"A": 4}, {"A": 4}, {"A": 4}, {"A": 4}, {"A": 4}, {"A": 4}, {"A": 4}, {"A": 4}, {"A": 4}, {"A": 4}, {"A": 4}, {"A": 5}, {"A": 4}, {"A": 4}]}, {"59": [{"A": 4}, {"A": 4}, {"A": 4}, {"A": 4}, {"A": 4}, {"A": 4}, {"A": 4}, {"A": 4}, {"A": 4}, {"A": 4}, {"A": 4}, {"A": 4}, {"A": 4}, {"A": 4}, {"A": 4}, {"A": 4}, {"A": 4}, {"A": 4}, {"A": 4}, {"A": 4}, {"A": 4}, {"A": 4}, {"A": 2}, {"A": 4}, {"A": 4}, {"A": 4}, {"A": 4}, {"A": 4}, {"A": 4}, {"A": 4}, {"A": 4}, {"A": 4}, {"A": 4}, {"A": 4}, {"A": 4}, {"A": 4}, {"A": 4}, {"A": 4}, {"A": 4}, {"A": 4}, {"A": 4}, {"A": 4}, {"A": 4}, {"A": 4}, {"A": 4}, {"A": 4}, {"A": 4}, {"A": 4}, {"A": 1}, {"A": 4}]}, {"60": [{"A": 1}, {"A": 4}, {"A": 4}, {"A": 1}, {"A": 1}, {"A": 4}, {"A": 1}, {"A": 1}, {"A": 1}, {"A": 1}, {"A": 4}, {"A": 4}, {"A": 4}, {"A": 1}, {"A": 4}, {"A": 1}, {"A": 4}, {"A": 1}, {"A": 4}, {"A": 1}, {"A": 1}, {"A": 1}, {"A": 4}, {"A": 4}, {"A": 1}, {"A": 4}, {"A": 1}, {"A": 4}, {"A": 4}, {"A": 4}, {"A": 4}, {"A": 1}, {"A": 4}, {"A": 1}, {"A": 4}, {"A": 4}, {"A": 4}, {"A": 1}, {"A": 4}, {"A": 4}, {"A": 1}, {"A": 4}, {"A": 4}, {"A": 4}, {"A": 4}, {"A": 4}, {"A": 1}, {"A": 4}, {"A": 1}, {"A": 1}]}, {"61": [{"A": 2}, {"A": 2}, {"A": 2}, {"A": 2}, {"A": 5}, {"A": 2}, {"A": 2}, {"A": 2}, {"A": 2}, {"A": 2}, {"A": 5}, {"A": 2}, {"A": 5}, {"A": 5}, {"A": 5}, {"A": 5}, {"A": 2}, {"A": 5}, {"A": 2}, {"A": 2}, {"A": 2}, {"A": 5}, {"A": 2}, {"A": 2}, {"A": 5}, {"A": 5}, {"A": 2}, {"A": 2}, {"A": 5}, {"A": 2}, {"A": 5}, {"A": 5}, {"A": 2}, {"A": 5}, {"A": 2}, {"A": 5}, {"A": 5}, {"A": 2}, {"A": 2}, {"A": 5}, {"A": 2}, {"A": 5}, {"A": 5}, {"A": 2}, {"A": 2}, {"A": 5}, {"A": 5}, {"A": 5}, {"A": 5}, {"A": 5}]}, {"62": [{"A": 2}, {"A": 4}, {"A": 4}, {"A": 4}, {"A": 2}, {"A": 4}, {"A": 2}, {"A": 4}, {"A": 2}, {"A": 2}, {"A": 4}, {"A": 2}, {"A": 4}, {"A": 2}, {"A": 2}, {"A": 4}, {"A": 4}, {"A": 2}, {"A": 2}, {"A": 2}, {"A": 4}, {"A": 4}, {"A": 2}, {"A": 2}, {"A": 4}, {"A": 2}, {"A": 2}, {"A": 2}, {"A": 4}, {"A": 2}, {"A": 2}, {"A": 2}, {"A": 4}, {"A": 2}, {"A": 4}, {"A": 4}, {"A": 4}, {"A": 4}, {"A": 4}, {"A": 2}, {"A": 2}, {"A": 4}, {"A": 4}, {"A": 2}, {"A": 2}, {"A": 4}, {"A": 4}, {"A": 4}, {"A": 4}, {"A": 4}]}, {"63": [{"A": 4}, {"A": 4}, {"A": 4}, {"A": 4}, {"A": 4}, {"A": 4}, {"A": 4}, {"A": 4}, {"A": 4}, {"A": 4}, {"A": 4}, {"A": 4}, {"A": 4}, {"A": 4}, {"A": 4}, {"A": 4}, {"A": 4}, {"A": 4}, {"A": 1}, {"A": 4}, {"A": 4}, {"A": 4}, {"A": 4}, {"A": 4}, {"A": 1}, {"A": 4}, {"A": 4}, {"A": 1}, {"A": 4}, {"A": 1}, {"A": 1}, {"A": 1}, {"A": 1}, {"A": 4}, {"A": 4}, {"A": 4}, {"A": 4}, {"A": 4}, {"A": 4}, {"A": 4}, {"A": 4}, {"A": 4}, {"A": 4}, {"A": 4}, {"A": 4}, {"A": 4}, {"A": 4}, {"A": 4}, {"A": 1}, {"A": 4}]}, {"64": [{"A": 3}, {"A": 3}, {"A": 3}, {"A": 3}, {"A": 3}, {"A": 3}, {"A": 3}, {"A": 3}, {"A": 3}, {"A": 3}, {"A": 3}, {"A": 3}, {"A": 3}, {"A": 3}, {"A": 4}, {"A": 3}, {"A": 3}, {"A": 3}, {"A": 3}, {"A": 3}, {"A": 3}, {"A": 3}, {"A": 3}, {"A": 3}, {"A": 3}, {"A": 3}, {"A": 3}, {"A": 3}, {"A": 3}, {"A": 3}, {"A": 3}, {"A": 3}, {"A": 3}, {"A": 3}, {"A": 3}, {"A": 3}, {"A": 3}, {"A": 3}, {"A": 3}, {"A": 3}, {"A": 3}, {"A": 3}, {"A": 3}, {"A": 3}, {"A": 3}, {"A": 3}, {"A": 3}, {"A": 3}, {"A": 2}, {"A": 3}]}, {"65": [{"A": 2}, {"A": 4}, {"A": 2}, {"A": 2}, {"A": 2}, {"A": 4}, {"A": 4}, {"A": 2}, {"A": 4}, {"A": 4}, {"A": 2}, {"A": 2}, {"A": 4}, {"A": 2}, {"A": 4}, {"A": 2}, {"A": 4}, {"A": 2}, {"A": 2}, {"A": 2}, {"A": 4}, {"A": 2}, {"A": 2}, {"A": 2}, {"A": 4}, {"A": 2}, {"A": 2}, {"A": 2}, {"A": 4}, {"A": 2}, {"A": 4}, {"A": 2}, {"A": 2}, {"A": 2}, {"A": 2}, {"A": 2}, {"A": 4}, {"A": 2}, {"A": 2}, {"A": 2}, {"A": 2}, {"A": 2}, {"A": 2}, {"A": 2}, {"A": 4}, {"A": 4}, {"A": 2}, {"A": 4}, {"A": 2}, {"A": 2}]}, {"66": [{"A": 2}, {"A": 2}, {"A": 4}, {"A": 4}, {"A": 2}, {"A": 2}, {"A": 2}, {"A": 2}, {"A": 2}, {"A": 2}, {"A": 2}, {"A": 4}, {"A": 2}, {"A": 4}, {"A": 4}, {"A": 2}, {"A": 2}, {"A": 4}, {"A": 4}, {"A": 4}, {"A": 4}, {"A": 4}, {"A": 2}, {"A": 2}, {"A": 2}, {"A": 2}, {"A": 4}, {"A": 4}, {"A": 4}, {"A": 2}, {"A": 2}, {"A": 2}, {"A": 2}, {"A": 2}, {"A": 4}, {"A": 4}, {"A": 2}, {"A": 2}, {"A": 2}, {"A": 4}, {"A": 4}, {"A": 2}, {"A": 2}, {"A": 4}, {"A": 2}, {"A": 4}, {"A": 4}, {"A": 2}, {"A": 4}, {"A": 2}]}, {"67": [{"A": 2}, {"A": 2}, {"A": 2}, {"A": 2}, {"A": 2}, {"A": 2}, {"A": 2}, {"A": 2}, {"A": 2}, {"A": 4}, {"A": 4}, {"A": 4}, {"A": 2}, {"A": 2}, {"A": 2}, {"A": 2}, {"A": 2}, {"A": 2}, {"A": 2}, {"A": 2}, {"A": 4}, {"A": 2}, {"A": 2}, {"A": 4}, {"A": 2}, {"A": 4}, {"A": 4}, {"A": 4}, {"A": 2}, {"A": 4}, {"A": 4}, {"A": 2}, {"A": 2}, {"A": 2}, {"A": 4}, {"A": 2}, {"A": 2}, {"A": 2}, {"A": 2}, {"A": 2}, {"A": 4}, {"A": 2}, {"A": 2}, {"A": 2}, {"A": 2}, {"A": 2}, {"A": 2}, {"A": 4}, {"A": 2}, {"A": 2}]}, {"68": [{"A": 4}, {"A": 4}, {"A": 4}, {"A": 4}, {"A": 4}, {"A": 4}, {"A": 4}, {"A": 4}, {"A": 4}, {"A": 4}, {"A": 4}, {"A": 4}, {"A": 4}, {"A": 4}, {"A": 4}, {"A": 4}, {"A": 4}, {"A": 4}, {"A": 4}, {"A": 4}, {"A": 4}, {"A": 4}, {"A": 4}, {"A": 4}, {"A": 4}, {"A": 4}, {"A": 4}, {"A": 4}, {"A": 4}, {"A": 4}, {"A": 4}, {"A": 4}, {"A": 4}, {"A": 4}, {"A": 4}, {"A": 4}, {"A": 4}, {"A": 4}, {"A": 4}, {"A": 4}, {"A": 4}, {"A": 4}, {"A": 4}, {"A": 4}, {"A": 4}, {"A": 4}, {"A": 4}, {"A": 4}, {"A": 4}, {"A": 4}]}, {"69": [{"A": 5}, {"A": 5}, {"A": 5}, {"A": 5}, {"A": 5}, {"A": 5}, {"A": 5}, {"A": 5}, {"A": 5}, {"A": 5}, {"A": 5}, {"A": 5}, {"A": 5}, {"A": 5}, {"A": 5}, {"A": 5}, {"A": 5}, {"A": 5}, {"A": 5}, {"A": 5}, {"A": 5}, {"A": 5}, {"A": 5}, {"A": 5}, {"A": 5}, {"A": 5}, {"A": 5}, {"A": 5}, {"A": 5}, {"A": 5}, {"A": 5}, {"A": 5}, {"A": 5}, {"A": 5}, {"A": 5}, {"A": 5}, {"A": 5}, {"A": 5}, {"A": 5}, {"A": 5}, {"A": 5}, {"A": 5}, {"A": 5}, {"A": 5}, {"A": 5}, {"A": 5}, {"A": 5}, {"A": 5}, {"A": 5}, {"A": 5}]}, {"70": [{"A": 4}, {"A": 4}, {"A": 4}, {"A": 4}, {"A": 4}, {"A": 4}, {"A": 4}, {"A": 4}, {"A": 4}, {"A": 4}, {"A": 4}, {"A": 4}, {"A": 4}, {"A": 4}, {"A": 4}, {"A": 4}, {"A": 4}, {"A": 4}, {"A": 4}, {"A": 6}, {"A": 4}, {"A": 4}, {"A": 4}, {"A": 4}, {"A": 4}, {"A": 4}, {"A": 4}, {"A": 4}, {"A": 4}, {"A": 6}, {"A": 4}, {"A": 4}, {"A": 4}, {"A": 4}, {"A": 4}, {"A": 4}, {"A": 4}, {"A": 4}, {"A": 4}, {"A": 4}, {"A": 4}, {"A": 4}, {"A": 4}, {"A": 4}, {"A": 4}, {"A": 4}, {"A": 4}, {"A": 4}, {"A": 4}, {"A": 4}]}, {"71": [{"A": 3}, {"A": 3}, {"A": 3}, {"A": 3}, {"A": 3}, {"A": 3}, {"A": 3}, {"A": 3}, {"A": 3}, {"A": 6}, {"A": 3}, {"A": 3}, {"A": 3}, {"A": 3}, {"A": 3}, {"A": 6}, {"A": 3}, {"A": 3}, {"A": 3}, {"A": 3}, {"A": 3}, {"A": 3}, {"A": 3}, {"A": 6}, {"A": 6}, {"A": 3}, {"A": 3}, {"A": 6}, {"A": 3}, {"A": 3}, {"A": 3}, {"A": 3}, {"A": 3}, {"A": 3}, {"A": 3}, {"A": 3}, {"A": 3}, {"A": 3}, {"A": 3}, {"A": 3}, {"A": 3}, {"A": 3}, {"A": 3}, {"A": 3}, {"A": 3}, {"A": 3}, {"A": 3}, {"A": 3}, {"A": 3}, {"A": 6}]}, {"72": [{"A": 4}, {"A": 4}, {"A": 4}, {"A": 4}, {"A": 4}, {"A": 2}, {"A": 4}, {"A": 4}, {"A": 4}, {"A": 4}, {"A": 4}, {"A": 4}, {"A": 2}, {"A": 4}, {"A": 4}, {"A": 4}, {"A": 4}, {"A": 2}, {"A": 4}, {"A": 4}, {"A": 2}, {"A": 4}, {"A": 2}, {"A": 4}, {"A": 2}, {"A": 4}, {"A": 4}, {"A": 4}, {"A": 4}, {"A": 4}, {"A": 4}, {"A": 4}, {"A": 4}, {"A": 4}, {"A": 2}, {"A": 4}, {"A": 4}, {"A": 2}, {"A": 4}, {"A": 4}, {"A": 2}, {"A": 4}, {"A": 4}, {"A": 4}, {"A": 4}, {"A": 4}, {"A": 4}, {"A": 4}, {"A": 2}, {"A": 4}]}, {"73": [{"A": 1}, {"A": 5}, {"A": 5}, {"A": 5}, {"A": 5}, {"A": 5}, {"A": 1}, {"A": 5}, {"A": 5}, {"A": 5}, {"A": 5}, {"A": 5}, {"A": 5}, {"A": 5}, {"A": 5}, {"A": 5}, {"A": 5}, {"A": 5}, {"A": 5}, {"A": 4}, {"A": 5}, {"A": 2}, {"A": 5}, {"A": 1}, {"A": 1}, {"A": 5}, {"A": 5}, {"A": 5}, {"A": 5}, {"A": 5}, {"A": 5}, {"A": 5}, {"A": 5}, {"A": 1}, {"A": 5}, {"A": 5}, {"A": 5}, {"A": 5}, {"A": 5}, {"A": 5}, {"A": 5}, {"A": 5}, {"A": 5}, {"A": 5}, {"A": 5}, {"A": 5}, {"A": 5}, {"A": 5}, {"A": 5}, {"A": 5}]}, {"74": [{"A": 1}, {"A": 1}, {"A": 4}, {"A": 4}, {"A": 1}, {"A": 4}, {"A": 4}, {"A": 4}, {"A": 4}, {"A": 1}, {"A": 1}, {"A": 4}, {"A": 1}, {"A": 1}, {"A": 1}, {"A": 4}, {"A": 4}, {"A": 4}, {"A": 1}, {"A": 4}, {"A": 4}, {"A": 4}, {"A": 4}, {"A": 4}, {"A": 4}, {"A": 1}, {"A": 4}, {"A": 1}, {"A": 1}, {"A": 1}, {"A": 1}, {"A": 1}, {"A": 1}, {"A": 1}, {"A": 4}, {"A": 4}, {"A": 4}, {"A": 4}, {"A": 4}, {"A": 4}, {"A": 4}, {"A": 4}, {"A": 4}, {"A": 1}, {"A": 1}, {"A": 4}, {"A": 4}, {"A": 4}, {"A": 1}, {"A": 4}]}, {"75": [{"A": 3}, {"A": 3}, {"A": 3}, {"A": 1}, {"A": 3}, {"A": 5}, {"A": 3}, {"A": 5}, {"A": 3}, {"A": 3}, {"A": 3}, {"A": 3}, {"A": 3}, {"A": 3}, {"A": 1}, {"A": 5}, {"A": 3}, {"A": 5}, {"A": 1}, {"A": 3}, {"A": 3}, {"A": 3}, {"A": 3}, {"A": 1}, {"A": 5}, {"A": 3}, {"A": 1}, {"A": 3}, {"A": 5}, {"A": 3}, {"A": 3}, {"A": 5}, {"A": 3}, {"A": 3}, {"A": 3}, {"A": 5}, {"A": 3}, {"A": 3}, {"A": 1}, {"A": 5}, {"A": 1}, {"A": 1}, {"A": 3}, {"A": 1}, {"A": 3}, {"A": 5}, {"A": 5}, {"A": 1}, {"A": 3}, {"A": 3}]}, {"76": [{"A": 5}, {"A": 5}, {"A": 3}, {"A": 3}, {"A": 5}, {"A": 3}, {"A": 3}, {"A": 3}, {"A": 3}, {"A": 3}, {"A": 3}, {"A": 3}, {"A": 5}, {"A": 5}, {"A": 3}, {"A": 5}, {"A": 3}, {"A": 3}, {"A": 3}, {"A": 3}, {"A": 3}, {"A": 3}, {"A": 3}, {"A": 3}, {"A": 3}, {"A": 3}, {"A": 3}, {"A": 3}, {"A": 3}, {"A": 3}, {"A": 5}, {"A": 3}, {"A": 3}, {"A": 3}, {"A": 5}, {"A": 3}, {"A": 3}, {"A": 3}, {"A": 3}, {"A": 3}, {"A": 5}, {"A": 3}, {"A": 3}, {"A": 3}, {"A": 3}, {"A": 3}, {"A": 3}, {"A": 5}, {"A": 3}, {"A": 3}]}, {"77": [{"A": 6}, {"A": 6}, {"A": 4}, {"A": 6}, {"A": 4}, {"A": 6}, {"A": 6}, {"A": 6}, {"A": 4}, {"A": 6}, {"A": 4}, {"A": 4}, {"A": 6}, {"A": 4}, {"A": 4}, {"A": 4}, {"A": 4}, {"A": 6}, {"A": 6}, {"A": 6}, {"A": 4}, {"A": 6}, {"A": 4}, {"A": 4}, {"A": 6}, {"A": 6}, {"A": 4}, {"A": 4}, {"A": 6}, {"A": 4}, {"A": 6}, {"A": 6}, {"A": 4}, {"A": 4}, {"A": 6}, {"A": 4}, {"A": 6}, {"A": 6}, {"A": 4}, {"A": 6}, {"A": 6}, {"A": 6}, {"A": 4}, {"A": 4}, {"A": 4}, {"A": 4}, {"A": 4}, {"A": 4}, {"A": 6}, {"A": 6}]}, {"78": [{"A": 4}, {"A": 4}, {"A": 4}, {"A": 4}, {"A": 4}, {"A": 4}, {"A": 4}, {"A": 4}, {"A": 4}, {"A": 4}, {"A": 4}, {"A": 4}, {"A": 4}, {"A": 4}, {"A": 4}, {"A": 4}, {"A": 4}, {"A": 4}, {"A": 4}, {"A": 4}, {"A": 4}, {"A": 4}, {"A": 4}, {"A": 4}, {"A": 4}, {"A": 4}, {"A": 4}, {"A": 4}, {"A": 4}, {"A": 4}, {"A": 4}, {"A": 4}, {"A": 4}, {"A": 4}, {"A": 4}, {"A": 4}, {"A": 4}, {"A": 4}, {"A": 4}, {"A": 4}, {"A": 4}, {"A": 4}, {"A": 4}, {"A": 4}, {"A": 4}, {"A": 4}, {"A": 4}, {"A": 4}, {"A": 4}, {"A": 4}]}, {"79": [{"A": 4}, {"A": 4}, {"A": 4}, {"A": 4}, {"A": 4}, {"A": 4}, {"A": 4}, {"A": 4}, {"A": 4}, {"A": 4}, {"A": 4}, {"A": 4}, {"A": 4}, {"A": 4}, {"A": 4}, {"A": 4}, {"A": 4}, {"A": 4}, {"A": 4}, {"A": 4}, {"A": 4}, {"A": 4}, {"A": 4}, {"A": 4}, {"A": 4}, {"A": 4}, {"A": 4}, {"A": 4}, {"A": 4}, {"A": 4}, {"A": 4}, {"A": 4}, {"A": 4}, {"A": 4}, {"A": 4}, {"A": 4}, {"A": 4}, {"A": 4}, {"A": 4}, {"A": 4}, {"A": 4}, {"A": 4}, {"A": 4}, {"A": 4}, {"A": 4}, {"A": 4}, {"A": 4}, {"A": 4}, {"A": 4}, {"A": 4}]}, {"80": [{"A": 4}, {"A": 4}, {"A": 4}, {"A": 4}, {"A": 4}, {"A": 4}, {"A": 4}, {"A": 4}, {"A": 4}, {"A": 4}, {"A": 4}, {"A": 4}, {"A": 4}, {"A": 4}, {"A": 4}, {"A": 4}, {"A": 4}, {"A": 4}, {"A": 4}, {"A": 4}, {"A": 4}, {"A": 4}, {"A": 4}, {"A": 4}, {"A": 4}, {"A": 4}, {"A": 4}, {"A": 4}, {"A": 4}, {"A": 4}, {"A": 4}, {"A": 4}, {"A": 4}, {"A": 4}, {"A": 4}, {"A": 4}, {"A": 4}, {"A": 4}, {"A": 4}, {"A": 4}, {"A": 4}, {"A": 4}, {"A": 4}, {"A": 4}, {"A": 4}, {"A": 4}, {"A": 4}, {"A": 4}, {"A": 4}, {"A": 4}]}, {"81": [{"A": 4}, {"A": 4}, {"A": 4}, {"A": 4}, {"A": 4}, {"A": 4}, {"A": 4}, {"A": 4}, {"A": 4}, {"A": 4}, {"A": 4}, {"A": 4}, {"A": 4}, {"A": 4}, {"A": 4}, {"A": 4}, {"A": 4}, {"A": 4}, {"A": 4}, {"A": 4}, {"A": 4}, {"A": 4}, {"A": 4}, {"A": 4}, {"A": 4}, {"A": 4}, {"A": 4}, {"A": 4}, {"A": 4}, {"A": 4}, {"A": 4}, {"A": 4}, {"A": 4}, {"A": 4}, {"A": 4}, {"A": 4}, {"A": 4}, {"A": 4}, {"A": 4}, {"A": 4}, {"A": 4}, {"A": 4}, {"A": 4}, {"A": 4}, {"A": 4}, {"A": 4}, {"A": 4}, {"A": 4}, {"A": 4}, {"A": 4}]}, {"82": [{"A": 4}, {"A": 4}, {"A": 4}, {"A": 4}, {"A": 4}, {"A": 4}, {"A": 4}, {"A": 4}, {"A": 4}, {"A": 4}, {"A": 4}, {"A": 4}, {"A": 4}, {"A": 4}, {"A": 4}, {"A": 4}, {"A": 4}, {"A": 4}, {"A": 3}, {"A": 4}, {"A": 4}, {"A": 4}, {"A": 4}, {"A": 4}, {"A": 4}, {"A": 4}, {"A": 4}, {"A": 4}, {"A": 4}, {"A": 4}, {"A": 4}, {"A": 4}, {"A": 4}, {"A": 4}, {"A": 4}, {"A": 4}, {"A": 4}, {"A": 4}, {"A": 4}, {"A": 4}, {"A": 4}, {"A": 4}, {"A": 4}, {"A": 4}, {"A": 4}, {"A": 4}, {"A": 4}, {"A": 4}, {"A": 4}, {"A": 4}]}, {"83": [{"A": 3}, {"A": 5}, {"A": 3}, {"A": 5}, {"A": 5}, {"A": 3}, {"A": 5}, {"A": 3}, {"A": 5}, {"A": 3}, {"A": 5}, {"A": 5}, {"A": 5}, {"A": 3}, {"A": 3}, {"A": 5}, {"A": 3}, {"A": 5}, {"A": 5}, {"A": 3}, {"A": 3}, {"A": 5}, {"A": 3}, {"A": 3}, {"A": 5}, {"A": 3}, {"A": 5}, {"A": 3}, {"A": 5}, {"A": 3}, {"A": 3}, {"A": 5}, {"A": 5}, {"A": 5}, {"A": 5}, {"A": 3}, {"A": 5}, {"A": 5}, {"A": 5}, {"A": 5}, {"A": 5}, {"A": 3}, {"A": 5}, {"A": 3}, {"A": 3}, {"A": 5}, {"A": 5}, {"A": 3}, {"A": 5}, {"A": 3}]}, {"84": [{"A": 5}, {"A": 5}, {"A": 5}, {"A": 5}, {"A": 5}, {"A": 5}, {"A": 5}, {"A": 4}, {"A": 5}, {"A": 5}, {"A": 5}, {"A": 5}, {"A": 5}, {"A": 5}, {"A": 5}, {"A": 5}, {"A": 5}, {"A": 5}, {"A": 5}, {"A": 5}, {"A": 5}, {"A": 5}, {"A": 5}, {"A": 5}, {"A": 5}, {"A": 5}, {"A": 5}, {"A": 2}, {"A": 5}, {"A": 5}, {"A": 5}, {"A": 5}, {"A": 5}, {"A": 5}, {"A": 5}, {"A": 5}, {"A": 5}, {"A": 5}, {"A": 5}, {"A": 5}, {"A": 5}, {"A": 5}, {"A": 5}, {"A": 5}, {"A": 5}, {"A": 5}, {"A": 5}, {"A": 5}, {"A": 5}, {"A": 5}]}, {"85": [{"A": 4}, {"A": 4}, {"A": 4}, {"A": 4}, {"A": 4}, {"A": 4}, {"A": 4}, {"A": 4}, {"A": 4}, {"A": 4}, {"A": 4}, {"A": 4}, {"A": 4}, {"A": 4}, {"A": 4}, {"A": 2}, {"A": 4}, {"A": 4}, {"A": 4}, {"A": 4}, {"A": 4}, {"A": 4}, {"A": 4}, {"A": 4}, {"A": 4}, {"A": 4}, {"A": 4}, {"A": 4}, {"A": 4}, {"A": 4}, {"A": 4}, {"A": 4}, {"A": 2}, {"A": 4}, {"A": 4}, {"A": 4}, {"A": 4}, {"A": 4}, {"A": 4}, {"A": 4}, {"A": 4}, {"A": 4}, {"A": 4}, {"A": 4}, {"A": 4}, {"A": 4}, {"A": 4}, {"A": 2}, {"A": 4}, {"A": 4}]}, {"86": [{"A": 5}, {"A": 5}, {"A": 5}, {"A": 5}, {"A": 5}, {"A": 5}, {"A": 5}, {"A": 5}, {"A": 5}, {"A": 5}, {"A": 5}, {"A": 5}, {"A": 5}, {"A": 5}, {"A": 5}, {"A": 5}, {"A": 5}, {"A": 5}, {"A": 5}, {"A": 5}, {"A": 5}, {"A": 5}, {"A": 5}, {"A": 5}, {"A": 5}, {"A": 5}, {"A": 5}, {"A": 5}, {"A": 5}, {"A": 5}, {"A": 5}, {"A": 5}, {"A": 5}, {"A": 5}, {"A": 5}, {"A": 5}, {"A": 5}, {"A": 5}, {"A": 5}, {"A": 5}, {"A": 5}, {"A": 5}, {"A": 5}, {"A": 5}, {"A": 5}, {"A": 5}, {"A": 5}, {"A": 5}, {"A": 5}, {"A": 5}]}, {"87": [{"A": 4}, {"A": 6}, {"A": 4}, {"A": 6}, {"A": 6}, {"A": 4}, {"A": 6}, {"A": 6}, {"A": 6}, {"A": 6}, {"A": 6}, {"A": 6}, {"A": 4}, {"A": 4}, {"A": 4}, {"A": 4}, {"A": 6}, {"A": 6}, {"A": 6}, {"A": 6}, {"A": 6}, {"A": 4}, {"A": 6}, {"A": 4}, {"A": 6}, {"A": 6}, {"A": 6}, {"A": 4}, {"A": 6}, {"A": 6}, {"A": 6}, {"A": 4}, {"A": 6}, {"A": 6}, {"A": 4}, {"A": 6}, {"A": 6}, {"A": 6}, {"A": 4}, {"A": 6}, {"A": 4}, {"A": 6}, {"A": 6}, {"A": 4}, {"A": 4}, {"A": 4}, {"A": 6}, {"A": 4}, {"A": 4}, {"A": 6}]}, {"88": [{"A": 3}, {"A": 3}, {"A": 3}, {"A": 3}, {"A": 3}, {"A": 3}, {"A": 3}, {"A": 3}, {"A": 3}, {"A": 3}, {"A": 3}, {"A": 3}, {"A": 3}, {"A": 3}, {"A": 3}, {"A": 4}, {"A": 3}, {"A": 3}, {"A": 3}, {"A": 3}, {"A": 3}, {"A": 3}, {"A": 3}, {"A": 3}, {"A": 3}, {"A": 3}, {"A": 3}, {"A": 3}, {"A": 3}, {"A": 3}, {"A": 3}, {"A": 3}, {"A": 3}, {"A": 3}, {"A": 3}, {"A": 3}, {"A": 3}, {"A": 3}, {"A": 3}, {"A": 3}, {"A": 3}, {"A": 3}, {"A": 3}, {"A": 3}, {"A": 3}, {"A": 3}, {"A": 3}, {"A": 3}, {"A": 3}, {"A": 3}]}, {"89": [{"A": 2}, {"A": 2}, {"A": 2}, {"A": 4}, {"A": 2}, {"A": 4}, {"A": 4}, {"A": 4}, {"A": 4}, {"A": 4}, {"A": 4}, {"A": 2}, {"A": 4}, {"A": 2}, {"A": 4}, {"A": 2}, {"A": 4}, {"A": 4}, {"A": 4}, {"A": 4}, {"A": 4}, {"A": 4}, {"A": 2}, {"A": 2}, {"A": 2}, {"A": 2}, {"A": 4}, {"A": 2}, {"A": 2}, {"A": 2}, {"A": 2}, {"A": 4}, {"A": 2}, {"A": 2}, {"A": 4}, {"A": 4}, {"A": 2}, {"A": 4}, {"A": 4}, {"A": 2}, {"A": 4}, {"A": 2}, {"A": 4}, {"A": 4}, {"A": 4}, {"A": 4}, {"A": 2}, {"A": 2}, {"A": 2}, {"A": 2}]}, {"90": [{"A": 2}, {"A": 5}, {"A": 5}, {"A": 2}, {"A": 5}, {"A": 2}, {"A": 5}, {"A": 2}, {"A": 2}, {"A": 2}, {"A": 2}, {"A": 2}, {"A": 2}, {"A": 5}, {"A": 5}, {"A": 2}, {"A": 2}, {"A": 2}, {"A": 2}, {"A": 5}, {"A": 2}, {"A": 5}, {"A": 2}, {"A": 2}, {"A": 2}, {"A": 2}, {"A": 2}, {"A": 5}, {"A": 2}, {"A": 2}, {"A": 2}, {"A": 2}, {"A": 2}, {"A": 2}, {"A": 5}, {"A": 2}, {"A": 2}, {"A": 2}, {"A": 2}, {"A": 2}, {"A": 2}, {"A": 5}, {"A": 5}, {"A": 2}, {"A": 2}, {"A": 2}, {"A": 5}, {"A": 2}, {"A": 5}, {"A": 5}]}, {"91": [{"A": 5}, {"A": 5}, {"A": 1}, {"A": 5}, {"A": 5}, {"A": 5}, {"A": 5}, {"A": 1}, {"A": 5}, {"A": 1}, {"A": 5}, {"A": 1}, {"A": 5}, {"A": 5}, {"A": 5}, {"A": 5}, {"A": 5}, {"A": 5}, {"A": 1}, {"A": 1}, {"A": 5}, {"A": 1}, {"A": 5}, {"A": 5}, {"A": 5}, {"A": 5}, {"A": 5}, {"A": 1}, {"A": 5}, {"A": 1}, {"A": 1}, {"A": 5}, {"A": 1}, {"A": 1}, {"A": 5}, {"A": 5}, {"A": 5}, {"A": 1}, {"A": 5}, {"A": 1}, {"A": 1}, {"A": 1}, {"A": 5}, {"A": 1}, {"A": 1}, {"A": 5}, {"A": 5}, {"A": 1}, {"A": 5}, {"A": 1}]}, {"92": [{"A": 4}, {"A": 2}, {"A": 2}, {"A": 2}, {"A": 2}, {"A": 2}, {"A": 2}, {"A": 2}, {"A": 4}, {"A": 2}, {"A": 2}, {"A": 4}, {"A": 4}, {"A": 2}, {"A": 2}, {"A": 2}, {"A": 2}, {"A": 2}, {"A": 2}, {"A": 4}, {"A": 2}, {"A": 2}, {"A": 4}, {"A": 2}, {"A": 2}, {"A": 4}, {"A": 2}, {"A": 2}, {"A": 2}, {"A": 4}, {"A": 4}, {"A": 2}, {"A": 2}, {"A": 2}, {"A": 2}, {"A": 2}, {"A": 2}, {"A": 4}, {"A": 4}, {"A": 2}, {"A": 2}, {"A": 2}, {"A": 2}, {"A": 2}, {"A": 4}, {"A": 2}, {"A": 2}, {"A": 2}, {"A": 2}, {"A": 2}]}, {"93": [{"A": 4}, {"A": 4}, {"A": 4}, {"A": 2}, {"A": 4}, {"A": 4}, {"A": 2}, {"A": 4}, {"A": 4}, {"A": 4}, {"A": 5}, {"A": 4}, {"A": 4}, {"A": 4}, {"A": 4}, {"A": 4}, {"A": 4}, {"A": 4}, {"A": 4}, {"A": 4}, {"A": 4}, {"A": 4}, {"A": 4}, {"A": 4}, {"A": 4}, {"A": 4}, {"A": 4}, {"A": 4}, {"A": 4}, {"A": 4}, {"A": 4}, {"A": 4}, {"A": 2}, {"A": 4}, {"A": 4}, {"A": 4}, {"A": 4}, {"A": 4}, {"A": 4}, {"A": 4}, {"A": 4}, {"A": 2}, {"A": 4}, {"A": 4}, {"A": 4}, {"A": 4}, {"A": 4}, {"A": 2}, {"A": 4}, {"A": 4}]}, {"94": [{"A": 4}, {"A": 4}, {"A": 4}, {"A": 4}, {"A": 4}, {"A": 4}, {"A": 4}, {"A": 4}, {"A": 4}, {"A": 4}, {"A": 4}, {"A": 4}, {"A": 4}, {"A": 4}, {"A": 4}, {"A": 4}, {"A": 4}, {"A": 4}, {"A": 4}, {"A": 4}, {"A": 4}, {"A": 4}, {"A": 4}, {"A": 4}, {"A": 4}, {"A": 4}, {"A": 4}, {"A": 4}, {"A": 4}, {"A": 4}, {"A": 4}, {"A": 4}, {"A": 4}, {"A": 4}, {"A": 4}, {"A": 4}, {"A": 4}, {"A": 4}, {"A": 4}, {"A": 4}, {"A": 4}, {"A": 4}, {"A": 4}, {"A": 4}, {"A": 4}, {"A": 4}, {"A": 4}, {"A": 4}, {"A": 4}, {"A": 4}]}, {"95": [{"A": 4}, {"A": 4}, {"A": 4}, {"A": 4}, {"A": 4}, {"A": 4}, {"A": 4}, {"A": 4}, {"A": 4}, {"A": 4}, {"A": 4}, {"A": 4}, {"A": 4}, {"A": 4}, {"A": 4}, {"A": 4}, {"A": 4}, {"A": 4}, {"A": 4}, {"A": 4}, {"A": 4}, {"A": 4}, {"A": 4}, {"A": 4}, {"A": 4}, {"A": 4}, {"A": 4}, {"A": 4}, {"A": 4}, {"A": 4}, {"A": 4}, {"A": 4}, {"A": 4}, {"A": 4}, {"A": 4}, {"A": 4}, {"A": 4}, {"A": 4}, {"A": 4}, {"A": 4}, {"A": 4}, {"A": 4}, {"A": 4}, {"A": 4}, {"A": 4}, {"A": 4}, {"A": 4}, {"A": 4}, {"A": 4}, {"A": 4}]}, {"96": [{"A": 4}, {"A": 4}, {"A": 4}, {"A": 4}, {"A": 4}, {"A": 4}, {"A": 4}, {"A": 4}, {"A": 4}, {"A": 4}, {"A": 4}, {"A": 4}, {"A": 4}, {"A": 4}, {"A": 4}, {"A": 4}, {"A": 4}, {"A": 4}, {"A": 4}, {"A": 4}, {"A": 4}, {"A": 4}, {"A": 4}, {"A": 4}, {"A": 4}, {"A": 4}, {"A": 4}, {"A": 4}, {"A": 4}, {"A": 4}, {"A": 4}, {"A": 4}, {"A": 4}, {"A": 4}, {"A": 4}, {"A": 4}, {"A": 4}, {"A": 4}, {"A": 4}, {"A": 4}, {"A": 4}, {"A": 4}, {"A": 4}, {"A": 4}, {"A": 4}, {"A": 4}, {"A": 4}, {"A": 4}, {"A": 4}, {"A": 4}]}, {"97": [{"A": 4}, {"A": 4}, {"A": 4}, {"A": 4}, {"A": 4}, {"A": 4}, {"A": 4}, {"A": 4}, {"A": 4}, {"A": 4}, {"A": 4}, {"A": 4}, {"A": 4}, {"A": 4}, {"A": 4}, {"A": 4}, {"A": 4}, {"A": 4}, {"A": 4}, {"A": 4}, {"A": 4}, {"A": 4}, {"A": 4}, {"A": 4}, {"A": 4}, {"A": 4}, {"A": 4}, {"A": 4}, {"A": 4}, {"A": 4}, {"A": 4}, {"A": 4}, {"A": 4}, {"A": 4}, {"A": 4}, {"A": 4}, {"A": 4}, {"A": 4}, {"A": 4}, {"A": 4}, {"A": 4}, {"A": 4}, {"A": 4}, {"A": 4}, {"A": 4}, {"A": 4}, {"A": 4}, {"A": 4}, {"A": 4}, {"A": 4}]}, {"98": [{"A": 4}, {"A": 4}, {"A": 4}, {"A": 4}, {"A": 4}, {"A": 4}, {"A": 4}, {"A": 4}, {"A": 4}, {"A": 4}, {"A": 4}, {"A": 4}, {"A": 4}, {"A": 4}, {"A": 4}, {"A": 4}, {"A": 4}, {"A": 4}, {"A": 4}, {"A": 4}, {"A": 4}, {"A": 4}, {"A": 4}, {"A": 4}, {"A": 4}, {"A": 4}, {"A": 4}, {"A": 4}, {"A": 4}, {"A": 4}, {"A": 4}, {"A": 4}, {"A": 4}, {"A": 4}, {"A": 4}, {"A": 4}, {"A": 4}, {"A": 4}, {"A": 4}, {"A": 4}, {"A": 4}, {"A": 4}, {"A": 4}, {"A": 4}, {"A": 4}, {"A": 4}, {"A": 4}, {"A": 4}, {"A": 4}, {"A": 4}]}, {"99": [{"A": 3}, {"A": 3}, {"A": 3}, {"A": 3}, {"A": 3}, {"A": 3}, {"A": 3}, {"A": 3}, {"A": 3}, {"A": 3}, {"A": 3}, {"A": 3}, {"A": 3}, {"A": 3}, {"A": 3}, {"A": 3}, {"A": 3}, {"A": 3}, {"A": 3}, {"A": 3}, {"A": 3}, {"A": 3}, {"A": 3}, {"A": 3}, {"A": 3}, {"A": 4}, {"A": 3}, {"A": 3}, {"A": 3}, {"A": 3}, {"A": 3}, {"A": 3}, {"A": 3}, {"A": 3}, {"A": 3}, {"A": 3}, {"A": 3}, {"A": 3}, {"A": 3}, {"A": 3}, {"A": 3}, {"A": 3}, {"A": 3}, {"A": 3}, {"A": 3}, {"A": 3}, {"A": 3}, {"A": 3}, {"A": 3}, {"A": 3}]}]